{"key":"content:fr:video-courses:index.md","generatedAt":"2022-03-15T12:18:23.903Z","mtime":"2022-03-15T12:18:23.885Z","slug":"","title":"Cours vidéos Nuxt","position":"999999990000","to":"/video-courses","draft":false,"page":true,"language":"fr","template":"blog","description":"Apprenez-en plus sur le framework Nuxt avec ce choix de vidéos en anglais, gratuites ou premium.","empty":false,"body":{"raw":"---\ntemplate: blog\ntitle: Cours vidéos Nuxt\ndescription: \"Apprenez-en plus sur le framework Nuxt avec ce choix de vidéos en anglais, gratuites ou premium.\"\n---\n\n::video-courses-list\n---\nvideo-courses:\n  one:\n    title: Apprenez Nuxt en créant une application du monde réel\n    description: Apprenez à créer des sites web robustes et modernes avec Nuxt à partir de zéro. Ou améliorez les performances de votre site web, la qualité du code, tout en utilisant mieux le framework.\n    image: /img/video-courses/mastering_nuxt.png\n    link: 'https://masteringnuxt.com/?utm_source=nuxt&utm_medium=link&utm_campaign=navbar_link'\n    tier: Premium\n  two:\n    title: Démarrer avec Nuxt\n    description: Apprenez l'essentiel pour créer et déployer un site Nuxt, y compris les routes dynamiques, la récupération de données, le référencement, le chargement en arrière plan, les styles globaux et les transitions, ainsi que comment générer et déployer votre application Nuxt.\n    image: /img/video-courses/jamstack_explorer.png\n    link: 'https://explorers.netlify.com/learn/get-started-with-nuxt'\n    tier: Gratuit\n  three:\n    title: Apprenez Nuxt avec Debbie\n    description: Une liste de lecture de vidéos YouTube couvrant tout ce qui concerne Nuxt, y compris de courtes vidéos et des livestreams.\n    image: /img/video-courses/learn_nuxt_with_debbie.png\n    link: 'https://www.youtube.com/c/DebbieOBrien'\n    tier: Gratuit\n  four:\n    title: Création d'applications avec Vue et Nuxt\n    description: Créez des applications Web dynamiques avec Vue et Nuxt ! Tout au long du cours, vous développerez une variété de projets en tirant parti des outils de l'écosystème Vue, notamment Vue CLI, Nuxt, Vuex Store, etc.\n    image: /img/video-courses/building_applications_fe_masters.png\n    link: 'https://frontendmasters.com/courses/vue-nuxt-apps/'\n    tier: Premium\n  five:\n    title: Construisez un tableau de Job avec Laravel, GraphQL, Nuxt et Apollo\n    description: Apprenez pendant que vous créez une API GraphQL avec Laravel Lighthouse, puis créez une interface Nuxt avec Apollo pour la consommer. Le tout stylisé avec Tailwind.\n    image: /img/video-courses/job_board.png\n    link: 'https://codecourse.com/courses/build-a-job-board-with-laravel-graphql-nuxt-and-apollo'\n    tier: Premium\n  six:\n    title: Nuxt - Vue.js sur Steroids\n    description: Créez des applications Vue JS très attrayantes avec Nuxt. Nuxt ajoute un rendu côté serveur facile et une approche de configuration basée sur les dossiers.\n    image: /img/video-courses/vuejs_on_steroids.png\n    link: 'https://www.udemy.com/course/nuxtjs-vuejs-on-steroids/'\n    tier: Premium\n  seven:\n    title: Mise à l'échelle de Vue avec Nuxt\n    description: Une fois que vous êtes à l'aise avec Vue, l'apprentissage d'un framework comme Nuxt vous permet de créer des applications Web prêtes pour la production qui suivent les meilleures pratiques.\n    image: /img/video-courses/scaling_vue_with_nuxt.png\n    link: 'https://www.vuemastery.com/courses/scaling-vue-with-nuxt-js/why-use-nuxt'\n    tier: Premium\n  eight:\n    title: Les fondamentales de Nuxt\n    description: Apprenez les bases de Nuxt dans ce cours que nous avons créé avec les fondateurs de Nuxt. Le cours couvre ce que vous devez savoir, de l'échafaudage au déploiement de votre première application Nuxt.\n    image: /img/video-courses/nuxt_fundamentals.png\n    link: 'https://vueschool.io/courses/nuxtjs-fundamentals?friend=nuxt&utm_source=Nuxtjs.org&utm_medium=Link&utm_content=Courses&utm_campaign=nuxtjs-fundamentals'\n    tier: Gratuit\n  nine:\n    title: Créer une application d'actualités avec Vue.js et Nuxt\n    description: Vous apprendrez à créer des pages dynamiques pour chaque section de votre application et à charger, stocker, afficher, filtrer et styliser les données. Ensuite, le résultat final sera une application d'actualités avec plusieurs pages de catégories, des commentaires pour chaque section et des pages utilisateurs.\n    image: /img/video-courses/news_app.png\n    link: 'https://egghead.io/courses/create-a-news-app-with-vue-js-and-nuxt'\n    tier: Gratuit\n---\n::\n","ast":{"type":"root","children":[{"type":"element","tag":"video-courses-list","props":{":video-courses":"{\"one\":{\"title\":\"Apprenez Nuxt en créant une application du monde réel\",\"description\":\"Apprenez à créer des sites web robustes et modernes avec Nuxt à partir de zéro. Ou améliorez les performances de votre site web, la qualité du code, tout en utilisant mieux le framework.\",\"image\":\"/img/video-courses/mastering_nuxt.png\",\"link\":\"https://masteringnuxt.com/?utm_source=nuxt&utm_medium=link&utm_campaign=navbar_link\",\"tier\":\"Premium\"},\"two\":{\"title\":\"Démarrer avec Nuxt\",\"description\":\"Apprenez l'essentiel pour créer et déployer un site Nuxt, y compris les routes dynamiques, la récupération de données, le référencement, le chargement en arrière plan, les styles globaux et les transitions, ainsi que comment générer et déployer votre application Nuxt.\",\"image\":\"/img/video-courses/jamstack_explorer.png\",\"link\":\"https://explorers.netlify.com/learn/get-started-with-nuxt\",\"tier\":\"Gratuit\"},\"three\":{\"title\":\"Apprenez Nuxt avec Debbie\",\"description\":\"Une liste de lecture de vidéos YouTube couvrant tout ce qui concerne Nuxt, y compris de courtes vidéos et des livestreams.\",\"image\":\"/img/video-courses/learn_nuxt_with_debbie.png\",\"link\":\"https://www.youtube.com/c/DebbieOBrien\",\"tier\":\"Gratuit\"},\"four\":{\"title\":\"Création d'applications avec Vue et Nuxt\",\"description\":\"Créez des applications Web dynamiques avec Vue et Nuxt ! Tout au long du cours, vous développerez une variété de projets en tirant parti des outils de l'écosystème Vue, notamment Vue CLI, Nuxt, Vuex Store, etc.\",\"image\":\"/img/video-courses/building_applications_fe_masters.png\",\"link\":\"https://frontendmasters.com/courses/vue-nuxt-apps/\",\"tier\":\"Premium\"},\"five\":{\"title\":\"Construisez un tableau de Job avec Laravel, GraphQL, Nuxt et Apollo\",\"description\":\"Apprenez pendant que vous créez une API GraphQL avec Laravel Lighthouse, puis créez une interface Nuxt avec Apollo pour la consommer. Le tout stylisé avec Tailwind.\",\"image\":\"/img/video-courses/job_board.png\",\"link\":\"https://codecourse.com/courses/build-a-job-board-with-laravel-graphql-nuxt-and-apollo\",\"tier\":\"Premium\"},\"six\":{\"title\":\"Nuxt - Vue.js sur Steroids\",\"description\":\"Créez des applications Vue JS très attrayantes avec Nuxt. Nuxt ajoute un rendu côté serveur facile et une approche de configuration basée sur les dossiers.\",\"image\":\"/img/video-courses/vuejs_on_steroids.png\",\"link\":\"https://www.udemy.com/course/nuxtjs-vuejs-on-steroids/\",\"tier\":\"Premium\"},\"seven\":{\"title\":\"Mise à l'échelle de Vue avec Nuxt\",\"description\":\"Une fois que vous êtes à l'aise avec Vue, l'apprentissage d'un framework comme Nuxt vous permet de créer des applications Web prêtes pour la production qui suivent les meilleures pratiques.\",\"image\":\"/img/video-courses/scaling_vue_with_nuxt.png\",\"link\":\"https://www.vuemastery.com/courses/scaling-vue-with-nuxt-js/why-use-nuxt\",\"tier\":\"Premium\"},\"eight\":{\"title\":\"Les fondamentales de Nuxt\",\"description\":\"Apprenez les bases de Nuxt dans ce cours que nous avons créé avec les fondateurs de Nuxt. Le cours couvre ce que vous devez savoir, de l'échafaudage au déploiement de votre première application Nuxt.\",\"image\":\"/img/video-courses/nuxt_fundamentals.png\",\"link\":\"https://vueschool.io/courses/nuxtjs-fundamentals?friend=nuxt&utm_source=Nuxtjs.org&utm_medium=Link&utm_content=Courses&utm_campaign=nuxtjs-fundamentals\",\"tier\":\"Gratuit\"},\"nine\":{\"title\":\"Créer une application d'actualités avec Vue.js et Nuxt\",\"description\":\"Vous apprendrez à créer des pages dynamiques pour chaque section de votre application et à charger, stocker, afficher, filtrer et styliser les données. Ensuite, le résultat final sera une application d'actualités avec plusieurs pages de catégories, des commentaires pour chaque section et des pages utilisateurs.\",\"image\":\"/img/video-courses/news_app.png\",\"link\":\"https://egghead.io/courses/create-a-news-app-with-vue-js-and-nuxt\",\"tier\":\"Gratuit\"}}"},"children":[]}]},"toc":{"title":"","searchDepth":2,"depth":2,"links":[]}}}