{"key":"content:ja:design:index.md","generatedAt":"2022-03-15T12:18:28.717Z","mtime":"2022-03-15T12:18:28.713Z","slug":"","title":"Design Kit","position":"999999990000","to":"/design","draft":false,"page":true,"language":"ja","template":"blank","description":"Learn how to use Nuxt logos, colors and fonts and download the design kit.","layout":{"fluid":true},"navigation":false,"empty":false,"body":{"raw":"---\ntemplate: blank\ntitle: 'Design Kit'\ndescription: 'Learn how to use Nuxt logos, colors and fonts and download the design kit.'\nlayout:\n  fluid: true\nnavigation: false\n---\n\n::design-hero\n---\ntitle: Nuxt デザインキット\ndescription: \"Nuxt は MIT ライセンスされたオープンソースプロジェクトで利用は完全に無料です。Nuxt について言及し、nuxtjs.org にリンクしている場合に限り、私たちのロゴを自由に使用することができます。\"\ndownloadText: デザインキットをダウンロード\n---\n::\n\n::design-sections\n\n  ::design-section\n  #title\n  モノグラム\n  #description\n  私たちのロゴは三角形の山とワードマークの2つの要素から作られています。ほとんの場合、それらは反対側のマスターロックアップが示すように、これらは一緒に表示されるべきです。三角形の山は、アイコンやプロフィール写真、バッジとして単独で使用することができますが、ワードマークは、このシンボルを横に置かずに使用することはできません。\n  #sectionComponent\n    :::design-logos\n    ---\n    type: monogram\n    ---\n    :::\n  ::\n\n  ::design-section\n  #title\n  ロゴ\n  #sectionComponent\n    :::design-logos\n    ---\n    type: logos\n    ---\n    :::\n  ::\n\n  ::design-section\n  #title\n  プライマリカラー\n  #description\n  私たちのカラーは、様々なメディアで調和と一貫性を持って機能するように慎重に検討されています。Nuxt のコミュニケーションを作成する際には、以下のページに示されているカラーバリューを使用して、デザインがブランドに沿ったものであることを確認してください。この自然にインスパイアされたプライマリーカラーパレットは、会社関連の正式なコミュニケーションのすべてに使用する必要があります。\n  #sectionComponent\n    :::design-colors\n    ---\n    buttonText: カラーシステムをダウンロード\n    ---\n    :::\n  ::\n\n  ::design-section\n  #title\n  タイポグラフィ\n  #description\n  私たちのブランド書体は、Colophon Foundry 社が Google のために開発した DM Sans です。このオープンソースの書体が選ばれた理由は、滑らかさと構造の組み合わせです。幾何学的な形と柔らかな変化が、私たちのテキストに明快さと開放感をもたらします。私たちのテキストに明快さと開放感をもたらします。また、オープンソースなので、Nuxt コミュニティの他のメンバーが作品に取り入れることもできます。自分の作品に取り入れることができます。\n  #sectionComponent\n    :::design-typography\n    :::\n  ::\n::\n","ast":{"type":"root","children":[{"type":"element","tag":"design-hero","props":{"description":"Nuxt は MIT ライセンスされたオープンソースプロジェクトで利用は完全に無料です。Nuxt について言及し、nuxtjs.org にリンクしている場合に限り、私たちのロゴを自由に使用することができます。","downloadText":"デザインキットをダウンロード","title":"Nuxt デザインキット"},"children":[]},{"type":"text","value":"\n"},{"type":"element","tag":"design-sections","props":{},"children":[{"type":"element","tag":"design-section","props":{},"children":[{"type":"element","tag":"template","props":{"v-slot:title":""},"children":[{"type":"element","tag":"prose-paragraph","props":{},"children":[{"type":"text","value":"モノグラム"}]}],"content":[{"type":"element","tag":"prose-paragraph","props":{},"children":[{"type":"text","value":"モノグラム"}]}]},{"type":"element","tag":"template","props":{"v-slot:description":""},"children":[{"type":"element","tag":"prose-paragraph","props":{},"children":[{"type":"text","value":"私たちのロゴは三角形の山とワードマークの2つの要素から作られています。ほとんの場合、それらは反対側のマスターロックアップが示すように、これらは一緒に表示されるべきです。三角形の山は、アイコンやプロフィール写真、バッジとして単独で使用することができますが、ワードマークは、このシンボルを横に置かずに使用することはできません。"}]}],"content":[{"type":"element","tag":"prose-paragraph","props":{},"children":[{"type":"text","value":"私たちのロゴは三角形の山とワードマークの2つの要素から作られています。ほとんの場合、それらは反対側のマスターロックアップが示すように、これらは一緒に表示されるべきです。三角形の山は、アイコンやプロフィール写真、バッジとして単独で使用することができますが、ワードマークは、このシンボルを横に置かずに使用することはできません。"}]}]},{"type":"element","tag":"template","props":{"v-slot:sectionComponent":""},"children":[{"type":"element","tag":"design-logos","props":{"type":"monogram"},"children":[]}],"content":[{"type":"element","tag":"design-logos","props":{"type":"monogram"},"children":[]}]}]},{"type":"element","tag":"design-section","props":{},"children":[{"type":"element","tag":"template","props":{"v-slot:title":""},"children":[{"type":"element","tag":"prose-paragraph","props":{},"children":[{"type":"text","value":"ロゴ"}]}],"content":[{"type":"element","tag":"prose-paragraph","props":{},"children":[{"type":"text","value":"ロゴ"}]}]},{"type":"element","tag":"template","props":{"v-slot:sectionComponent":""},"children":[{"type":"element","tag":"design-logos","props":{"type":"logos"},"children":[]}],"content":[{"type":"element","tag":"design-logos","props":{"type":"logos"},"children":[]}]}]},{"type":"element","tag":"design-section","props":{},"children":[{"type":"element","tag":"template","props":{"v-slot:title":""},"children":[{"type":"element","tag":"prose-paragraph","props":{},"children":[{"type":"text","value":"プライマリカラー"}]}],"content":[{"type":"element","tag":"prose-paragraph","props":{},"children":[{"type":"text","value":"プライマリカラー"}]}]},{"type":"element","tag":"template","props":{"v-slot:description":""},"children":[{"type":"element","tag":"prose-paragraph","props":{},"children":[{"type":"text","value":"私たちのカラーは、様々なメディアで調和と一貫性を持って機能するように慎重に検討されています。Nuxt のコミュニケーションを作成する際には、以下のページに示されているカラーバリューを使用して、デザインがブランドに沿ったものであることを確認してください。この自然にインスパイアされたプライマリーカラーパレットは、会社関連の正式なコミュニケーションのすべてに使用する必要があります。"}]}],"content":[{"type":"element","tag":"prose-paragraph","props":{},"children":[{"type":"text","value":"私たちのカラーは、様々なメディアで調和と一貫性を持って機能するように慎重に検討されています。Nuxt のコミュニケーションを作成する際には、以下のページに示されているカラーバリューを使用して、デザインがブランドに沿ったものであることを確認してください。この自然にインスパイアされたプライマリーカラーパレットは、会社関連の正式なコミュニケーションのすべてに使用する必要があります。"}]}]},{"type":"element","tag":"template","props":{"v-slot:sectionComponent":""},"children":[{"type":"element","tag":"design-colors","props":{"buttonText":"カラーシステムをダウンロード"},"children":[]}],"content":[{"type":"element","tag":"design-colors","props":{"buttonText":"カラーシステムをダウンロード"},"children":[]}]}]},{"type":"element","tag":"design-section","props":{},"children":[{"type":"element","tag":"template","props":{"v-slot:title":""},"children":[{"type":"element","tag":"prose-paragraph","props":{},"children":[{"type":"text","value":"タイポグラフィ"}]}],"content":[{"type":"element","tag":"prose-paragraph","props":{},"children":[{"type":"text","value":"タイポグラフィ"}]}]},{"type":"element","tag":"template","props":{"v-slot:description":""},"children":[{"type":"element","tag":"prose-paragraph","props":{},"children":[{"type":"text","value":"私たちのブランド書体は、Colophon Foundry 社が Google のために開発した DM Sans です。このオープンソースの書体が選ばれた理由は、滑らかさと構造の組み合わせです。幾何学的な形と柔らかな変化が、私たちのテキストに明快さと開放感をもたらします。私たちのテキストに明快さと開放感をもたらします。また、オープンソースなので、Nuxt コミュニティの他のメンバーが作品に取り入れることもできます。自分の作品に取り入れることができます。"}]}],"content":[{"type":"element","tag":"prose-paragraph","props":{},"children":[{"type":"text","value":"私たちのブランド書体は、Colophon Foundry 社が Google のために開発した DM Sans です。このオープンソースの書体が選ばれた理由は、滑らかさと構造の組み合わせです。幾何学的な形と柔らかな変化が、私たちのテキストに明快さと開放感をもたらします。私たちのテキストに明快さと開放感をもたらします。また、オープンソースなので、Nuxt コミュニティの他のメンバーが作品に取り入れることもできます。自分の作品に取り入れることができます。"}]}]},{"type":"element","tag":"template","props":{"v-slot:sectionComponent":""},"children":[{"type":"element","tag":"design-typography","props":{},"children":[]}],"content":[{"type":"element","tag":"design-typography","props":{},"children":[]}]}]}]}]},"toc":{"title":"","searchDepth":2,"depth":2,"links":[]}}}