{"key":"content:fr:index.md","generatedAt":"2022-03-15T12:18:22.935Z","mtime":"2022-03-15T12:18:22.909Z","slug":"","title":"Le framework Vue intuitif","position":"999900000000","to":"/","draft":false,"page":true,"language":"fr","template":"blank","description":"Construisez votre prochaine application Vue.js en toute confiance avec Nuxt. Un framework open source qui rend le développement web simple et puissant.","bgClass":"bg-white","empty":false,"body":{"raw":"---\ntemplate: blank\ntitle: 'Le framework Vue intuitif'\ndescription: 'Construisez votre prochaine application Vue.js en toute confiance avec Nuxt. Un framework open source qui rend le développement web simple et puissant.'\nbgClass: 'bg-white'\n---\n\n::home-hero\n#title\nLe framework Vue<br>intuitif\n\n#description\nConstruisez votre prochaine application Vue.js en toute confiance avec Nuxt.<br class=\"hidden sm:block\" /> Un framework open source qui rend le développement web simple et puissant.\n\n#primary-button\n:app-button[39K+ GitHub stars]{ href=\"https://github.com/nuxt/nuxt.js\" icon=\"IconGitHub\" extraClass=\"text-white bg-sky-black hover:bg-sky-darker leading-4\" }\n\n#secondary-button\n:app-button[Commencer]{ to=\"/docs/get-started/installation\" extraClass=\"text-black bg-primary-500 hover:bg-primary-400 focus:ring-primary-600 py-4\" }\n::\n\n::home-learn-master\n---\ncategory: Apprendre\n---\n\n#title\n[_Facile_]{.text-primary} à apprendre. [_Facile_]{.text-primary} à maîtriser\n\n#description\nTout ce que vous devez savoir, pour passer de débutant à expert.\n\n#bottom\n:app-button[Commencer le voyage]{href=\"/docs/get-started/installation\" size=\"medium\"}\n::\n\n::home-features\n---\ncategory: Fonctionnalités\n---\n  ::section-content-item\n  ---\n  title: Zero Configuration\n  description: \"Commencez tout de suite à coder, Nuxt s'occupe du reste.\"\n  image: /img/home/discover/dx/zero-config.svg\n  ---\n  ::\n  ::section-content-item\n  ---\n  title: Routing par système de fichiers\n  description: 'Routing automatique et code-splitting sur chaque page.'\n  image: /img/home/discover/dx/file-system-routing.svg\n  ---\n  ::\n  ::section-content-item\n  ---\n  title: Modes de rendu\n  description: \"Passez d'une génération statique à un rendu côté serveur à la demande.\"\n  image: /img/home/discover/dx/hybrid.svg\n  ---\n  ::\n  ::section-content-item\n  ---\n  title: Récupération de données\n  description: \"Récupérez votre contenu depuis n'importe quelle source, dans vos composants Vue, prêts pour un rendu serveur.\"\n  image: /img/home/discover/dx/fetch.svg\n  ---\n  ::\n  ::section-content-item\n  ---\n  title: Conventions fortes\n  description: \"Un travail d'équipe efficace avec une structure de dossiers et des conventions fortes.\"\n  image: /img/home/discover/dx/conventions.svg\n  ---\n  ::\n  ::section-content-item\n  ---\n  title: SEO Friendly\n  description: \"Gestion des balises Meta et time-to-content plus rapide pour une bonne indexation.\"\n  image: /img/home/discover/dx/seo.svg\n  ---\n  ::\n  ::section-content-item\n  ---\n  title: Auto-import des composants\n  description: \"Utilisez vos composants, Nuxt les importera avec un code-splitting intelligent.\"\n  image: /img/home/discover/dx/auto-inject.svg\n  ---\n  ::\n  ::section-content-item\n  ---\n  title: Ecosystème de modules\n  description: \"Etendez votre application avec plus de 160 modules Nuxt, et créez le vôtre.\"\n  image: /img/home/discover/dx/modular.svg\n  ---\n---\n  ::\n#title\nIntuitive [D]{.text-primary}eveloper E[x]{.text-primary}perience\n\n#description\nNuxt contient de nombreuses fonctionnalités améliorant l'expérience de développement et l'expérience de l'utilisateur final.\n::\n\n::home-discover-partners\n---\ncategory: Partenaires\n---\n\n#title\nUn [_développement_]{.text-primary} soutenu\n\n#description\nNuxt est construit et maintenu par des développeurs passionnés mais il serait impossible de fournir les efforts nécessaires pour développer et maintenir de nouvelles fonctionnalités sans une réelle contribution financière. Nous remercions nos sponsors et partenaires qui rendent cela possible.<br>\n\n#partners-card\n  ::home-partners-card\n  ---\n  icon: technology.svg\n  category: technology\n  ---\n  #title\n  Technology partners\n\n  #description\n  Les Technology partners offrent des services aux développeurs Nuxt, tels que CMS, hébergement, base de données, et plus encore...\n\n  #button\n  Découvrez nos Technology Partners\n  ::\n\n  ::home-partners-card\n  ---\n  icon: agency.svg\n  category: agency\n  ---\n  #title\n  Agency partners\n\n  #description\n  Les Agency partners sont des agences web reconnues qui proposent du support et du développement d'applications avec Nuxt.\n\n  #button\n  Trouvez un expert Nuxt\n  ::\n\n#bottom\n  :app-button[Devenez un partenaire]{href=\"mailto:partners@nuxtlabs.com\"}\n::\n\n::home-learn-guides\n---\ncategory: Apprendre\n---\n  ::section-content-item\n  ---\n  title: Documentation\n  description: \"Apprenez les concepts et fonctionnalités de Nuxt, du débutant à l'expert.\"\n  image: /img/home/learn/guides/gem-1.svg\n  to: '/docs/get-started/installation'\n  hoverClass: 'hover:bg-sky-darker'\n  ---\n  ::\n\n  ::section-content-item\n  ---\n  title: Exemples\n  description: \"Apprenez grâce aux exemples créés par la communauté.\"\n  image: /img/home/learn/guides/gem-2.svg\n  to: '/examples'\n  hoverClass: 'hover:bg-sky-darker'\n  ---\n  ::\n\n  ::section-content-item\n  ---\n  title: Notes de version\n  description: \"Découvrez ce qui a changé dans chaque mise à jour.\"\n  image: /img/home/learn/guides/gem-3.svg\n  to: '/releases'\n  hoverClass: 'hover:bg-sky-darker'\n  ---\n  ::\n\n  ::section-content-item\n  ---\n  title: Master Courses\n  description: 'Visionnez une série complète de vidéos pour apprendre Nuxt avec notre partenaire Vue School.'\n  image: /img/home/learn/guides/gem-4.svg\n  to: 'https://masteringnuxt.com/?utm_source=nuxt&utm_medium=link&utm_campaign=nsite'\n  hoverClass: 'hover:bg-sky-darker'\n  ---\n  ::\n\n#title\nSuivez nos [_Guides_]{.text-primary}\n\n#description\nFrom an Idea to a Masterpiece, guides show the path to become a Nuxter.\n::\n\n::home-explore\n---\ncategory: Explorez\n---\n  ::section-content-item\n  ---\n  title: 'Déploiements'\n  description: \"Étendez et automatisez votre flux de travail en utilisant les déploiements pour vos outils préférés.\"\n  image: '/img/home/explore/gem-explore-1.svg'\n  to: '/deployments'\n  hoverClass: 'hover:bg-sky-surface'\n  ---\n  ::\n  ::section-content-item\n  ---\n  title: 'Modules'\n  description: \"Découvrez la liste des modules pour étendre vos projects Nuxt. Créés par l'équipe de Nuxt et sa communauté\"\n  image: '/img/home/explore/gem-explore-2.svg'\n  to: 'https://modules.nuxtjs.org'\n  hoverClass: 'hover:bg-sky-surface'\n  ---\n  ::\n  ::section-content-item\n  ---\n  title: 'Themes'\n  description: \"Découvrez comment une application du monde réel est construite à l'aide de Nuxt avec les thèmes construits par nos partenaires.\"\n  image: '/img/home/explore/gem-explore-3.svg'\n  to: '/themes'\n  hoverClass: 'hover:bg-sky-surface'\n  ---\n  ::\n\n#title\nBesoin d'aller plus loin ? Il y a tellement à [_Explorer_]{.text-primary}\n\n#description\nNuxt a beaucoup de dimensions à explorer, apprenez par l'exemple, intégrez des fournisseurs externes ou commencez plus vite avec un thème.\n\n::\n\n::home-community\n---\ncategory: Communauté\nannouncementsCategory: Annonces\neventsCategory: Evénements\narticleLinkTitle: Informations\n---\n\n#title\nSharing is [_Caring_]{.text-primary}\n\n#description\nLisez nos articles rédigés par l'équipe Nuxt et la communauté, trucs et astuces inclus !\n::\n\n::home-testimonials\n---\ncategory: Communauté\n---\n#title\nTémoignages\n\n#description\nApprenez ce que les experts aiment chez Nuxt.\n\n#testimonials\n  :::testimonials\n  ---\n  home: true\n  ---\n  :::\n::\n","ast":{"type":"root","children":[{"type":"element","tag":"home-hero","props":{},"children":[{"type":"element","tag":"template","props":{"v-slot:title":""},"children":[{"type":"element","tag":"prose-paragraph","props":{},"children":[{"type":"text","value":"Le framework Vue"},{"type":"element","tag":"br","props":{},"children":[]},{"type":"text","value":"intuitif"}]}],"content":[{"type":"element","tag":"prose-paragraph","props":{},"children":[{"type":"text","value":"Le framework Vue"},{"type":"element","tag":"br","props":{},"children":[]},{"type":"text","value":"intuitif"}]}]},{"type":"element","tag":"template","props":{"v-slot:description":""},"children":[{"type":"element","tag":"prose-paragraph","props":{},"children":[{"type":"text","value":"Construisez votre prochaine application Vue.js en toute confiance avec Nuxt."},{"type":"element","tag":"br","props":{"className":["hidden","sm:block"]},"children":[]},{"type":"text","value":" Un framework open source qui rend le développement web simple et puissant."}]}],"content":[{"type":"element","tag":"prose-paragraph","props":{},"children":[{"type":"text","value":"Construisez votre prochaine application Vue.js en toute confiance avec Nuxt."},{"type":"element","tag":"br","props":{"className":["hidden","sm:block"]},"children":[]},{"type":"text","value":" Un framework open source qui rend le développement web simple et puissant."}]}]},{"type":"element","tag":"template","props":{"v-slot:primary-button":""},"children":[{"type":"element","tag":"app-button","props":{"href":"https://github.com/nuxt/nuxt.js","extraClass":"text-white bg-sky-black hover:bg-sky-darker leading-4","icon":"IconGitHub"},"children":[{"type":"text","value":"39K+ GitHub stars"}]}],"content":[{"type":"element","tag":"app-button","props":{"href":"https://github.com/nuxt/nuxt.js","extraClass":"text-white bg-sky-black hover:bg-sky-darker leading-4","icon":"IconGitHub"},"children":[{"type":"text","value":"39K+ GitHub stars"}]}]},{"type":"element","tag":"template","props":{"v-slot:secondary-button":""},"children":[{"type":"element","tag":"app-button","props":{"extraClass":"text-black bg-primary-500 hover:bg-primary-400 focus:ring-primary-600 py-4","to":"/docs/get-started/installation"},"children":[{"type":"text","value":"Commencer"}]}],"content":[{"type":"element","tag":"app-button","props":{"extraClass":"text-black bg-primary-500 hover:bg-primary-400 focus:ring-primary-600 py-4","to":"/docs/get-started/installation"},"children":[{"type":"text","value":"Commencer"}]}]}]},{"type":"text","value":"\n"},{"type":"element","tag":"home-learn-master","props":{"category":"Apprendre"},"children":[{"type":"element","tag":"template","props":{"v-slot:title":""},"children":[{"type":"element","tag":"prose-paragraph","props":{},"children":[{"type":"element","tag":"span","props":{"className":["text-primary"]},"children":[{"type":"element","tag":"prose-em","props":{},"children":[{"type":"text","value":"Facile"}]}]},{"type":"text","value":" à apprendre. "},{"type":"element","tag":"span","props":{"className":["text-primary"]},"children":[{"type":"element","tag":"prose-em","props":{},"children":[{"type":"text","value":"Facile"}]}]},{"type":"text","value":" à maîtriser"}]}],"content":[{"type":"element","tag":"prose-paragraph","props":{},"children":[{"type":"element","tag":"span","props":{"className":["text-primary"]},"children":[{"type":"element","tag":"prose-em","props":{},"children":[{"type":"text","value":"Facile"}]}]},{"type":"text","value":" à apprendre. "},{"type":"element","tag":"span","props":{"className":["text-primary"]},"children":[{"type":"element","tag":"prose-em","props":{},"children":[{"type":"text","value":"Facile"}]}]},{"type":"text","value":" à maîtriser"}]}]},{"type":"element","tag":"template","props":{"v-slot:description":""},"children":[{"type":"element","tag":"prose-paragraph","props":{},"children":[{"type":"text","value":"Tout ce que vous devez savoir, pour passer de débutant à expert."}]}],"content":[{"type":"element","tag":"prose-paragraph","props":{},"children":[{"type":"text","value":"Tout ce que vous devez savoir, pour passer de débutant à expert."}]}]},{"type":"element","tag":"template","props":{"v-slot:bottom":""},"children":[{"type":"element","tag":"app-button","props":{"href":"/docs/get-started/installation","size":"medium"},"children":[{"type":"text","value":"Commencer le voyage"}]}],"content":[{"type":"element","tag":"app-button","props":{"href":"/docs/get-started/installation","size":"medium"},"children":[{"type":"text","value":"Commencer le voyage"}]}]}]},{"type":"text","value":"\n"},{"type":"element","tag":"home-features","props":{"category":"Fonctionnalités"},"children":[{"type":"element","tag":"section-content-item","props":{"description":"Commencez tout de suite à coder, Nuxt s'occupe du reste.","image":"/img/home/discover/dx/zero-config.svg","title":"Zero Configuration"},"children":[]},{"type":"element","tag":"section-content-item","props":{"description":"Routing automatique et code-splitting sur chaque page.","image":"/img/home/discover/dx/file-system-routing.svg","title":"Routing par système de fichiers"},"children":[]},{"type":"element","tag":"section-content-item","props":{"description":"Passez d'une génération statique à un rendu côté serveur à la demande.","image":"/img/home/discover/dx/hybrid.svg","title":"Modes de rendu"},"children":[]},{"type":"element","tag":"section-content-item","props":{"description":"Récupérez votre contenu depuis n'importe quelle source, dans vos composants Vue, prêts pour un rendu serveur.","image":"/img/home/discover/dx/fetch.svg","title":"Récupération de données"},"children":[]},{"type":"element","tag":"section-content-item","props":{"description":"Un travail d'équipe efficace avec une structure de dossiers et des conventions fortes.","image":"/img/home/discover/dx/conventions.svg","title":"Conventions fortes"},"children":[]},{"type":"element","tag":"section-content-item","props":{"description":"Gestion des balises Meta et time-to-content plus rapide pour une bonne indexation.","image":"/img/home/discover/dx/seo.svg","title":"SEO Friendly"},"children":[]},{"type":"element","tag":"section-content-item","props":{"description":"Utilisez vos composants, Nuxt les importera avec un code-splitting intelligent.","image":"/img/home/discover/dx/auto-inject.svg","title":"Auto-import des composants"},"children":[]},{"type":"element","tag":"section-content-item","props":{"description":"Etendez votre application avec plus de 160 modules Nuxt, et créez le vôtre.","image":"/img/home/discover/dx/modular.svg","title":"Ecosystème de modules"},"children":[{"type":"element","tag":"prose-hr","props":{},"children":[]}]},{"type":"element","tag":"template","props":{"v-slot:title":""},"children":[{"type":"element","tag":"prose-paragraph","props":{},"children":[{"type":"text","value":"Intuitive "},{"type":"element","tag":"span","props":{"className":["text-primary"]},"children":[{"type":"text","value":"D"}]},{"type":"text","value":"eveloper E"},{"type":"element","tag":"span","props":{"className":["text-primary"]},"children":[{"type":"text","value":"x"}]},{"type":"text","value":"perience"}]}],"content":[{"type":"element","tag":"prose-paragraph","props":{},"children":[{"type":"text","value":"Intuitive "},{"type":"element","tag":"span","props":{"className":["text-primary"]},"children":[{"type":"text","value":"D"}]},{"type":"text","value":"eveloper E"},{"type":"element","tag":"span","props":{"className":["text-primary"]},"children":[{"type":"text","value":"x"}]},{"type":"text","value":"perience"}]}]},{"type":"element","tag":"template","props":{"v-slot:description":""},"children":[{"type":"element","tag":"prose-paragraph","props":{},"children":[{"type":"text","value":"Nuxt contient de nombreuses fonctionnalités améliorant l'expérience de développement et l'expérience de l'utilisateur final."}]}],"content":[{"type":"element","tag":"prose-paragraph","props":{},"children":[{"type":"text","value":"Nuxt contient de nombreuses fonctionnalités améliorant l'expérience de développement et l'expérience de l'utilisateur final."}]}]}]},{"type":"text","value":"\n"},{"type":"element","tag":"home-discover-partners","props":{"category":"Partenaires"},"children":[{"type":"element","tag":"template","props":{"v-slot:title":""},"children":[{"type":"element","tag":"prose-paragraph","props":{},"children":[{"type":"text","value":"Un "},{"type":"element","tag":"span","props":{"className":["text-primary"]},"children":[{"type":"element","tag":"prose-em","props":{},"children":[{"type":"text","value":"développement"}]}]},{"type":"text","value":" soutenu"}]}],"content":[{"type":"element","tag":"prose-paragraph","props":{},"children":[{"type":"text","value":"Un "},{"type":"element","tag":"span","props":{"className":["text-primary"]},"children":[{"type":"element","tag":"prose-em","props":{},"children":[{"type":"text","value":"développement"}]}]},{"type":"text","value":" soutenu"}]}]},{"type":"element","tag":"template","props":{"v-slot:description":""},"children":[{"type":"element","tag":"prose-paragraph","props":{},"children":[{"type":"text","value":"Nuxt est construit et maintenu par des développeurs passionnés mais il serait impossible de fournir les efforts nécessaires pour développer et maintenir de nouvelles fonctionnalités sans une réelle contribution financière. Nous remercions nos sponsors et partenaires qui rendent cela possible."},{"type":"element","tag":"br","props":{},"children":[]}]}],"content":[{"type":"element","tag":"prose-paragraph","props":{},"children":[{"type":"text","value":"Nuxt est construit et maintenu par des développeurs passionnés mais il serait impossible de fournir les efforts nécessaires pour développer et maintenir de nouvelles fonctionnalités sans une réelle contribution financière. Nous remercions nos sponsors et partenaires qui rendent cela possible."},{"type":"element","tag":"br","props":{},"children":[]}]}]},{"type":"element","tag":"template","props":{"v-slot:partners-card":""},"children":[{"type":"element","tag":"home-partners-card","props":{"category":"technology","icon":"technology.svg"},"children":[{"type":"element","tag":"template","props":{"v-slot:title":""},"children":[{"type":"element","tag":"prose-paragraph","props":{},"children":[{"type":"text","value":"Technology partners"}]}],"content":[{"type":"element","tag":"prose-paragraph","props":{},"children":[{"type":"text","value":"Technology partners"}]}]},{"type":"element","tag":"template","props":{"v-slot:description":""},"children":[{"type":"element","tag":"prose-paragraph","props":{},"children":[{"type":"text","value":"Les Technology partners offrent des services aux développeurs Nuxt, tels que CMS, hébergement, base de données, et plus encore..."}]}],"content":[{"type":"element","tag":"prose-paragraph","props":{},"children":[{"type":"text","value":"Les Technology partners offrent des services aux développeurs Nuxt, tels que CMS, hébergement, base de données, et plus encore..."}]}]},{"type":"element","tag":"template","props":{"v-slot:button":""},"children":[{"type":"element","tag":"prose-paragraph","props":{},"children":[{"type":"text","value":"Découvrez nos Technology Partners"}]}],"content":[{"type":"element","tag":"prose-paragraph","props":{},"children":[{"type":"text","value":"Découvrez nos Technology Partners"}]}]}]},{"type":"element","tag":"home-partners-card","props":{"category":"agency","icon":"agency.svg"},"children":[{"type":"element","tag":"template","props":{"v-slot:title":""},"children":[{"type":"element","tag":"prose-paragraph","props":{},"children":[{"type":"text","value":"Agency partners"}]}],"content":[{"type":"element","tag":"prose-paragraph","props":{},"children":[{"type":"text","value":"Agency partners"}]}]},{"type":"element","tag":"template","props":{"v-slot:description":""},"children":[{"type":"element","tag":"prose-paragraph","props":{},"children":[{"type":"text","value":"Les Agency partners sont des agences web reconnues qui proposent du support et du développement d'applications avec Nuxt."}]}],"content":[{"type":"element","tag":"prose-paragraph","props":{},"children":[{"type":"text","value":"Les Agency partners sont des agences web reconnues qui proposent du support et du développement d'applications avec Nuxt."}]}]},{"type":"element","tag":"template","props":{"v-slot:button":""},"children":[{"type":"element","tag":"prose-paragraph","props":{},"children":[{"type":"text","value":"Trouvez un expert Nuxt"}]}],"content":[{"type":"element","tag":"prose-paragraph","props":{},"children":[{"type":"text","value":"Trouvez un expert Nuxt"}]}]}]}],"content":[{"type":"element","tag":"home-partners-card","props":{"category":"technology","icon":"technology.svg"},"children":[{"type":"element","tag":"template","props":{"v-slot:title":""},"children":[{"type":"element","tag":"prose-paragraph","props":{},"children":[{"type":"text","value":"Technology partners"}]}],"content":[{"type":"element","tag":"prose-paragraph","props":{},"children":[{"type":"text","value":"Technology partners"}]}]},{"type":"element","tag":"template","props":{"v-slot:description":""},"children":[{"type":"element","tag":"prose-paragraph","props":{},"children":[{"type":"text","value":"Les Technology partners offrent des services aux développeurs Nuxt, tels que CMS, hébergement, base de données, et plus encore..."}]}],"content":[{"type":"element","tag":"prose-paragraph","props":{},"children":[{"type":"text","value":"Les Technology partners offrent des services aux développeurs Nuxt, tels que CMS, hébergement, base de données, et plus encore..."}]}]},{"type":"element","tag":"template","props":{"v-slot:button":""},"children":[{"type":"element","tag":"prose-paragraph","props":{},"children":[{"type":"text","value":"Découvrez nos Technology Partners"}]}],"content":[{"type":"element","tag":"prose-paragraph","props":{},"children":[{"type":"text","value":"Découvrez nos Technology Partners"}]}]}]},{"type":"element","tag":"home-partners-card","props":{"category":"agency","icon":"agency.svg"},"children":[{"type":"element","tag":"template","props":{"v-slot:title":""},"children":[{"type":"element","tag":"prose-paragraph","props":{},"children":[{"type":"text","value":"Agency partners"}]}],"content":[{"type":"element","tag":"prose-paragraph","props":{},"children":[{"type":"text","value":"Agency partners"}]}]},{"type":"element","tag":"template","props":{"v-slot:description":""},"children":[{"type":"element","tag":"prose-paragraph","props":{},"children":[{"type":"text","value":"Les Agency partners sont des agences web reconnues qui proposent du support et du développement d'applications avec Nuxt."}]}],"content":[{"type":"element","tag":"prose-paragraph","props":{},"children":[{"type":"text","value":"Les Agency partners sont des agences web reconnues qui proposent du support et du développement d'applications avec Nuxt."}]}]},{"type":"element","tag":"template","props":{"v-slot:button":""},"children":[{"type":"element","tag":"prose-paragraph","props":{},"children":[{"type":"text","value":"Trouvez un expert Nuxt"}]}],"content":[{"type":"element","tag":"prose-paragraph","props":{},"children":[{"type":"text","value":"Trouvez un expert Nuxt"}]}]}]}]},{"type":"element","tag":"template","props":{"v-slot:bottom":""},"children":[{"type":"element","tag":"app-button","props":{"href":"mailto:partners@nuxtlabs.com"},"children":[{"type":"text","value":"Devenez un partenaire"}]}],"content":[{"type":"element","tag":"app-button","props":{"href":"mailto:partners@nuxtlabs.com"},"children":[{"type":"text","value":"Devenez un partenaire"}]}]}]},{"type":"text","value":"\n"},{"type":"element","tag":"home-learn-guides","props":{"category":"Apprendre"},"children":[{"type":"element","tag":"section-content-item","props":{"description":"Apprenez les concepts et fonctionnalités de Nuxt, du débutant à l'expert.","image":"/img/home/learn/guides/gem-1.svg","title":"Documentation","hoverClass":"hover:bg-sky-darker","to":"/docs/get-started/installation"},"children":[]},{"type":"element","tag":"section-content-item","props":{"description":"Apprenez grâce aux exemples créés par la communauté.","image":"/img/home/learn/guides/gem-2.svg","title":"Exemples","hoverClass":"hover:bg-sky-darker","to":"/examples"},"children":[]},{"type":"element","tag":"section-content-item","props":{"description":"Découvrez ce qui a changé dans chaque mise à jour.","image":"/img/home/learn/guides/gem-3.svg","title":"Notes de version","hoverClass":"hover:bg-sky-darker","to":"/releases"},"children":[]},{"type":"element","tag":"section-content-item","props":{"description":"Visionnez une série complète de vidéos pour apprendre Nuxt avec notre partenaire Vue School.","image":"/img/home/learn/guides/gem-4.svg","title":"Master Courses","hoverClass":"hover:bg-sky-darker","to":"https://masteringnuxt.com/?utm_source=nuxt&utm_medium=link&utm_campaign=nsite"},"children":[]},{"type":"element","tag":"template","props":{"v-slot:title":""},"children":[{"type":"element","tag":"prose-paragraph","props":{},"children":[{"type":"text","value":"Suivez nos "},{"type":"element","tag":"span","props":{"className":["text-primary"]},"children":[{"type":"element","tag":"prose-em","props":{},"children":[{"type":"text","value":"Guides"}]}]}]}],"content":[{"type":"element","tag":"prose-paragraph","props":{},"children":[{"type":"text","value":"Suivez nos "},{"type":"element","tag":"span","props":{"className":["text-primary"]},"children":[{"type":"element","tag":"prose-em","props":{},"children":[{"type":"text","value":"Guides"}]}]}]}]},{"type":"element","tag":"template","props":{"v-slot:description":""},"children":[{"type":"element","tag":"prose-paragraph","props":{},"children":[{"type":"text","value":"From an Idea to a Masterpiece, guides show the path to become a Nuxter."}]}],"content":[{"type":"element","tag":"prose-paragraph","props":{},"children":[{"type":"text","value":"From an Idea to a Masterpiece, guides show the path to become a Nuxter."}]}]}]},{"type":"text","value":"\n"},{"type":"element","tag":"home-explore","props":{"category":"Explorez"},"children":[{"type":"element","tag":"section-content-item","props":{"description":"Étendez et automatisez votre flux de travail en utilisant les déploiements pour vos outils préférés.","image":"/img/home/explore/gem-explore-1.svg","title":"Déploiements","hoverClass":"hover:bg-sky-surface","to":"/deployments"},"children":[]},{"type":"element","tag":"section-content-item","props":{"description":"Découvrez la liste des modules pour étendre vos projects Nuxt. Créés par l'équipe de Nuxt et sa communauté","image":"/img/home/explore/gem-explore-2.svg","title":"Modules","hoverClass":"hover:bg-sky-surface","to":"https://modules.nuxtjs.org"},"children":[]},{"type":"element","tag":"section-content-item","props":{"description":"Découvrez comment une application du monde réel est construite à l'aide de Nuxt avec les thèmes construits par nos partenaires.","image":"/img/home/explore/gem-explore-3.svg","title":"Themes","hoverClass":"hover:bg-sky-surface","to":"/themes"},"children":[]},{"type":"element","tag":"template","props":{"v-slot:title":""},"children":[{"type":"element","tag":"prose-paragraph","props":{},"children":[{"type":"text","value":"Besoin d'aller plus loin ? Il y a tellement à "},{"type":"element","tag":"span","props":{"className":["text-primary"]},"children":[{"type":"element","tag":"prose-em","props":{},"children":[{"type":"text","value":"Explorer"}]}]}]}],"content":[{"type":"element","tag":"prose-paragraph","props":{},"children":[{"type":"text","value":"Besoin d'aller plus loin ? Il y a tellement à "},{"type":"element","tag":"span","props":{"className":["text-primary"]},"children":[{"type":"element","tag":"prose-em","props":{},"children":[{"type":"text","value":"Explorer"}]}]}]}]},{"type":"element","tag":"template","props":{"v-slot:description":""},"children":[{"type":"element","tag":"prose-paragraph","props":{},"children":[{"type":"text","value":"Nuxt a beaucoup de dimensions à explorer, apprenez par l'exemple, intégrez des fournisseurs externes ou commencez plus vite avec un thème."}]}],"content":[{"type":"element","tag":"prose-paragraph","props":{},"children":[{"type":"text","value":"Nuxt a beaucoup de dimensions à explorer, apprenez par l'exemple, intégrez des fournisseurs externes ou commencez plus vite avec un thème."}]}]}]},{"type":"text","value":"\n"},{"type":"element","tag":"home-community","props":{"announcementsCategory":"Annonces","articleLinkTitle":"Informations","category":"Communauté","eventsCategory":"Evénements"},"children":[{"type":"element","tag":"template","props":{"v-slot:title":""},"children":[{"type":"element","tag":"prose-paragraph","props":{},"children":[{"type":"text","value":"Sharing is "},{"type":"element","tag":"span","props":{"className":["text-primary"]},"children":[{"type":"element","tag":"prose-em","props":{},"children":[{"type":"text","value":"Caring"}]}]}]}],"content":[{"type":"element","tag":"prose-paragraph","props":{},"children":[{"type":"text","value":"Sharing is "},{"type":"element","tag":"span","props":{"className":["text-primary"]},"children":[{"type":"element","tag":"prose-em","props":{},"children":[{"type":"text","value":"Caring"}]}]}]}]},{"type":"element","tag":"template","props":{"v-slot:description":""},"children":[{"type":"element","tag":"prose-paragraph","props":{},"children":[{"type":"text","value":"Lisez nos articles rédigés par l'équipe Nuxt et la communauté, trucs et astuces inclus !"}]}],"content":[{"type":"element","tag":"prose-paragraph","props":{},"children":[{"type":"text","value":"Lisez nos articles rédigés par l'équipe Nuxt et la communauté, trucs et astuces inclus !"}]}]}]},{"type":"text","value":"\n"},{"type":"element","tag":"home-testimonials","props":{"category":"Communauté"},"children":[{"type":"element","tag":"template","props":{"v-slot:title":""},"children":[{"type":"element","tag":"prose-paragraph","props":{},"children":[{"type":"text","value":"Témoignages"}]}],"content":[{"type":"element","tag":"prose-paragraph","props":{},"children":[{"type":"text","value":"Témoignages"}]}]},{"type":"element","tag":"template","props":{"v-slot:description":""},"children":[{"type":"element","tag":"prose-paragraph","props":{},"children":[{"type":"text","value":"Apprenez ce que les experts aiment chez Nuxt."}]}],"content":[{"type":"element","tag":"prose-paragraph","props":{},"children":[{"type":"text","value":"Apprenez ce que les experts aiment chez Nuxt."}]}]},{"type":"element","tag":"template","props":{"v-slot:testimonials":""},"children":[{"type":"element","tag":"testimonials","props":{":home":"true"},"children":[]}],"content":[{"type":"element","tag":"testimonials","props":{":home":"true"},"children":[]}]}]}]},"toc":{"title":"","searchDepth":2,"depth":2,"links":[]}}}