{"key":"content:fr:design:index.md","generatedAt":"2022-03-15T12:18:23.435Z","mtime":"2022-03-15T12:18:23.428Z","slug":"","title":"Design Kit","position":"999999990000","to":"/design","draft":false,"page":true,"language":"fr","template":"blank","description":"Découvrez comment utiliser nos logos, couleurs et télécharger notre design kit.","layout":{"fluid":true},"navigation":false,"empty":false,"body":{"raw":"---\ntemplate: blank\ntitle: 'Design Kit'\ndescription: 'Découvrez comment utiliser nos logos, couleurs et télécharger notre design kit.'\nlayout:\n  fluid: true\nnavigation: false\n---\n\n::design-hero\n---\ntitle: Design Kit Nuxt\ndescription: \"Nuxt est un projet open source sous license MIT et totalement libre d'utilisation.\nVous pouvez télécharger gratuitement nos logos tant qu'une mention est faite de Nuxt et un lien vers nuxtjs.org.\"\ndownloadText : Téléchargez le Design Kit\n---\n::\n\n::design-sections\n\n  ::design-section\n  #title\n  Monogramme\n\n  #description\n  Notre logo est formé de deux éléments: les montagnes triangulaires et le nom. Dans la plupart des cas, ils doivent apparaître ensemble comme sur les exemples ci-joint. Les montagnes triangulaires peuvent être utilisées seules en tant qu'icône, image de profil ou badge, mais le logo-nom ne doit jamais être utilisé sans le symbôle à ses côtés.\n\n  #sectionComponent\n    :::design-logos\n    ---\n    type: monogram\n    ---\n    :::\n  ::\n\n  ::design-section\n  #title\n  Logos\n\n  #sectionComponent\n    :::design-logos\n    ---\n    type: logos\n    ---\n    :::\n  ::\n\n  ::design-section\n  #title\n  Primary colors\n\n  #description\n  Nos couleurs ont été soigneusement choisies pour fonctionner de façon harmonieuse et consistente dans une large variété de medias. Lorsque vous créez un support de communication pour Nuxt, utilisez les valeurs colorimétriques détaillées dans les pages suivantes pour que vos compositions restent alignés avec la marque. Cette palette de couleurs primaires inspirées par la nature doit être utilisée dans chacune des communications officielles de l'organisation.\n\n  #sectionComponent\n    :::design-colors\n    ---\n    buttonText: Télécharger les couleurs système\n    ---\n    :::\n  ::\n\n  ::design-section\n\n  #title\n  Typographie\n\n  #description\n  Notre typographie est DM Sans par Colophon Foundry pour Google. Cette typographie open-source a été retenue pour son alliage de douceur et structure. Ses formes géométriques et transitions douces apportent clarté et aération à nos textes.\n  Sa disponibilité publique laisse la liberté aux membres de la communauté Nuxt de l'incorporer dans leurs propres travaux.\n\n  #sectionComponent\n    :::design-typography\n    :::\n  ::\n::\n","ast":{"type":"root","children":[{"type":"element","tag":"design-hero","props":{"description":"Nuxt est un projet open source sous license MIT et totalement libre d'utilisation. Vous pouvez télécharger gratuitement nos logos tant qu'une mention est faite de Nuxt et un lien vers nuxtjs.org.","downloadText":"Téléchargez le Design Kit","title":"Design Kit Nuxt"},"children":[]},{"type":"text","value":"\n"},{"type":"element","tag":"design-sections","props":{},"children":[{"type":"element","tag":"design-section","props":{},"children":[{"type":"element","tag":"template","props":{"v-slot:title":""},"children":[{"type":"element","tag":"prose-paragraph","props":{},"children":[{"type":"text","value":"Monogramme"}]}],"content":[{"type":"element","tag":"prose-paragraph","props":{},"children":[{"type":"text","value":"Monogramme"}]}]},{"type":"element","tag":"template","props":{"v-slot:description":""},"children":[{"type":"element","tag":"prose-paragraph","props":{},"children":[{"type":"text","value":"Notre logo est formé de deux éléments: les montagnes triangulaires et le nom. Dans la plupart des cas, ils doivent apparaître ensemble comme sur les exemples ci-joint. Les montagnes triangulaires peuvent être utilisées seules en tant qu'icône, image de profil ou badge, mais le logo-nom ne doit jamais être utilisé sans le symbôle à ses côtés."}]}],"content":[{"type":"element","tag":"prose-paragraph","props":{},"children":[{"type":"text","value":"Notre logo est formé de deux éléments: les montagnes triangulaires et le nom. Dans la plupart des cas, ils doivent apparaître ensemble comme sur les exemples ci-joint. Les montagnes triangulaires peuvent être utilisées seules en tant qu'icône, image de profil ou badge, mais le logo-nom ne doit jamais être utilisé sans le symbôle à ses côtés."}]}]},{"type":"element","tag":"template","props":{"v-slot:sectionComponent":""},"children":[{"type":"element","tag":"design-logos","props":{"type":"monogram"},"children":[]}],"content":[{"type":"element","tag":"design-logos","props":{"type":"monogram"},"children":[]}]}]},{"type":"element","tag":"design-section","props":{},"children":[{"type":"element","tag":"template","props":{"v-slot:title":""},"children":[{"type":"element","tag":"prose-paragraph","props":{},"children":[{"type":"text","value":"Logos"}]}],"content":[{"type":"element","tag":"prose-paragraph","props":{},"children":[{"type":"text","value":"Logos"}]}]},{"type":"element","tag":"template","props":{"v-slot:sectionComponent":""},"children":[{"type":"element","tag":"design-logos","props":{"type":"logos"},"children":[]}],"content":[{"type":"element","tag":"design-logos","props":{"type":"logos"},"children":[]}]}]},{"type":"element","tag":"design-section","props":{},"children":[{"type":"element","tag":"template","props":{"v-slot:title":""},"children":[{"type":"element","tag":"prose-paragraph","props":{},"children":[{"type":"text","value":"Primary colors"}]}],"content":[{"type":"element","tag":"prose-paragraph","props":{},"children":[{"type":"text","value":"Primary colors"}]}]},{"type":"element","tag":"template","props":{"v-slot:description":""},"children":[{"type":"element","tag":"prose-paragraph","props":{},"children":[{"type":"text","value":"Nos couleurs ont été soigneusement choisies pour fonctionner de façon harmonieuse et consistente dans une large variété de medias. Lorsque vous créez un support de communication pour Nuxt, utilisez les valeurs colorimétriques détaillées dans les pages suivantes pour que vos compositions restent alignés avec la marque. Cette palette de couleurs primaires inspirées par la nature doit être utilisée dans chacune des communications officielles de l'organisation."}]}],"content":[{"type":"element","tag":"prose-paragraph","props":{},"children":[{"type":"text","value":"Nos couleurs ont été soigneusement choisies pour fonctionner de façon harmonieuse et consistente dans une large variété de medias. Lorsque vous créez un support de communication pour Nuxt, utilisez les valeurs colorimétriques détaillées dans les pages suivantes pour que vos compositions restent alignés avec la marque. Cette palette de couleurs primaires inspirées par la nature doit être utilisée dans chacune des communications officielles de l'organisation."}]}]},{"type":"element","tag":"template","props":{"v-slot:sectionComponent":""},"children":[{"type":"element","tag":"design-colors","props":{"buttonText":"Télécharger les couleurs système"},"children":[]}],"content":[{"type":"element","tag":"design-colors","props":{"buttonText":"Télécharger les couleurs système"},"children":[]}]}]},{"type":"element","tag":"design-section","props":{},"children":[{"type":"element","tag":"template","props":{"v-slot:title":""},"children":[{"type":"element","tag":"prose-paragraph","props":{},"children":[{"type":"text","value":"Typographie"}]}],"content":[{"type":"element","tag":"prose-paragraph","props":{},"children":[{"type":"text","value":"Typographie"}]}]},{"type":"element","tag":"template","props":{"v-slot:description":""},"children":[{"type":"element","tag":"prose-paragraph","props":{},"children":[{"type":"text","value":"Notre typographie est DM Sans par Colophon Foundry pour Google. Cette typographie open-source a été retenue pour son alliage de douceur et structure. Ses formes géométriques et transitions douces apportent clarté et aération à nos textes.\nSa disponibilité publique laisse la liberté aux membres de la communauté Nuxt de l'incorporer dans leurs propres travaux."}]}],"content":[{"type":"element","tag":"prose-paragraph","props":{},"children":[{"type":"text","value":"Notre typographie est DM Sans par Colophon Foundry pour Google. Cette typographie open-source a été retenue pour son alliage de douceur et structure. Ses formes géométriques et transitions douces apportent clarté et aération à nos textes.\nSa disponibilité publique laisse la liberté aux membres de la communauté Nuxt de l'incorporer dans leurs propres travaux."}]}]},{"type":"element","tag":"template","props":{"v-slot:sectionComponent":""},"children":[{"type":"element","tag":"design-typography","props":{},"children":[]}],"content":[{"type":"element","tag":"design-typography","props":{},"children":[]}]}]}]}]},"toc":{"title":"","searchDepth":2,"depth":2,"links":[]}}}