{"key":"content:es:index.md","generatedAt":"2022-03-15T12:18:25.394Z","mtime":"2022-03-15T12:18:25.373Z","slug":"","title":"El Framework de Vue Intuitivo","position":"999999990000","to":"/es","draft":false,"page":true,"language":"en","template":"blank","description":"Cree su próxima aplicación Vue.js con confianza usando Nuxt. Un framework de código abierto que hace que el desarrollo web sea simple y poderoso.","bgClass":"bg-white","empty":false,"body":{"raw":"---\ntemplate: blank\ntitle: 'El Framework de Vue Intuitivo'\ndescription: 'Cree su próxima aplicación Vue.js con confianza usando Nuxt. Un framework de código abierto que hace que el desarrollo web sea simple y poderoso.'\nbgClass: 'bg-white'\n---\n\n::home-hero\n#title\nEl Framework de Vue<br>Intuitivo\n\n#description\nCree su próxima aplicación Vue.js con confianza usando Nuxt.<br class=\"hidden sm:block\" /> Un framework de código abierto que hace que el desarrollo web sea simple y poderoso.\n\n#primary-button\n:app-button[39K+ GitHub stars]{ href=\"https://github.com/nuxt/nuxt.js\" icon=\"IconGitHub\" extraClass=\"text-white bg-sky-black hover:bg-sky-darker leading-4\" }\n\n#secondary-button\n:app-button[Comenzar]{ to=\"/docs/get-started/installation\" }\n::\n\n::home-learn-master\n---\ncategory: Aprender\n---\n\n#title\n[Fácil]{.text-primary} de aprender. [Fácil]{.text-primary} de dominar\n\n#description\nAprende todo lo que usted necesita saber, desde principiante hasta maestro.\n\n#bottom\n:app-button[Empieza a aprender]{to=\"/docs/get-started/installation\"}\n::\n\n::home-features\n---\ncategory: Características\n---\n\n::section-content-item\n---\ntitle: Sin configuraciones\ndescription: 'Comience a programar su aplicación de inmediato, Nuxt se encarga del resto.'\nimage: /img/home/discover/dx/zero-config.svg\n---\n::\n\n::section-content-item\n---\ntitle: Enrutamiento basado en archivos\ndescription: 'Enrutamiento automático y división de código para cada página.'\nimage: /img/home/discover/dx/file-system-routing.svg\n---\n::\n\n::section-content-item\n---\ntitle: Modos de renderizado\ndescription: 'Cambie entre la generación de sitios estáticos o renderizado en el servidor bajo demanda.'\nimage: /img/home/discover/dx/hybrid.svg\n---\n::\n\n::section-content-item\n---\ntitle: Obtención de datos\ndescription: 'Obtenga su contenido de cualquier fuente en sus componentes de Vue, listo para SSR.'\nimage: /img/home/discover/dx/fetch.svg\n---\n::\n\n::section-content-item\n---\ntitle: Convenios fuertes\ndescription: 'Trabajo en equipo eficiente con una sólida estructura de directorios y convenciones.'\nimage: /img/home/discover/dx/conventions.svg\n---\n::\n\n::section-content-item\n---\ntitle: SEO amigable\ndescription: 'Gestión de metaetiquetas y un tiempo de acceso al contenido más rápido para una excelente indexación.'\nimage: /img/home/discover/dx/seo.svg\n---\n::\n\n::section-content-item\n---\ntitle: Importación automática de componentes\ndescription: 'Use sus componentes, Nuxt los importará con división de código inteligente.'\nimage: /img/home/discover/dx/auto-inject.svg\n---\n::\n\n::section-content-item\n---\ntitle: Ecosistema de módulos\ndescription: 'Amplíe su aplicación con más de 160 módulos para Nuxt y cree los suyos propios.'\nimage: /img/home/discover/dx/modular.svg\n---\n::\n\n#title\nIntuitivo [D]{.text-primary}eveloper E[x]{.text-primary}perience\n\n#description\nNuxt se produce con muchas características para aumentar la productividad del desarrollador y la experiencia del usuario final.\n::\n\n::home-discover-partners\n---\ncategory: Partners\n---\n\n#title\nDesarrollo [_Sostenible_]{.text-primary}\n\n#description\nEl desarrollo de Nuxt lo llevan a cabo desarrolladores apasionados, pero la cantidad de esfuerzo necesario para mantener y desarrollar nuevas funciones no es sostenible sin el respaldo financiero adecuado. Agradecemos a nuestros patrocinadores y socios, que ayudan a hacer posible Nuxt.<br>\n\n#partners-card\n  ::home-partners-card\n  ---\n  icon: technology.svg\n  category: technology\n  ---\n  #title\n  Technology partners\n\n  #description\n  Technology partners offer services that empower Nuxt developers, such as CMS, Hosting, Database, and more.\n\n  #button\n  Discover our technology partners\n  ::\n\n  ::home-partners-card\n  ---\n  icon: agency.svg\n  category: agency\n  ---\n  #title\n  Agency partners\n\n  #description\n  Agency partners are trusted web and consulting agencies that can provide Nuxt development and support for your projects.\n\n  #button\n  Find a Nuxt expert\n  ::\n\n#bottom\n  :app-button[Conviertete en un patrocinador]{href=\"mailto:partners@nuxtlabs.com\"}\n::\n\n::home-learn-guides\n---\ncategory: Aprender\n---\n\n::section-content-item\n---\ntitle: Documentación\ndescription: 'Descubra los conceptos de Nuxt y encuentre una referencia completa del API.'\nimage: /img/home/learn/guides/gem-1.svg\nto: '/docs/get-started/installation'\nhoverClass: 'hover:bg-sky-darker'\n---\n::\n\n::section-content-item\n---\ntitle: Ejemplos\ndescription: \"Aprenda con ejemplos producidos por la comunidad.\"\nimage: /img/home/learn/guides/gem-2.svg\nto: '/examples'\nhoverClass: 'hover:bg-sky-darker'\n---\n::\n\n::section-content-item\n---\ntitle: Lanzamientos\ndescription: 'Descubra qué ha cambiado antes de actualizar.'\nimage: /img/home/learn/guides/gem-3.svg\nto: '/releases'\nhoverClass: 'hover:bg-sky-darker'\n---\n::\n\n::section-content-item\n---\ntitle: Cursos de Maestría\ndescription: 'Vea una serie completa de videos para aprender Nuxt con nuestro socio Vue School.'\nimage: /img/home/learn/guides/gem-4.svg\nto: 'https://masteringnuxt.com/?utm_source=nuxt&utm_medium=link&utm_campaign=nsite'\nhoverClass: 'hover:bg-sky-darker'\n---\n::\n\n#title\nSigue nuestra [_Guías_]{.text-primary}\n\n#description\nDesde una idea hasta una obra maestra, las guías lo llevarán por el camino para convertirse en un Nuxter.\n::\n\n::home-explore\n---\ncategory: Explorar\n---\n\n::section-content-item\n---\ntitle: 'Integraciones'\ndescription: 'Amplíe y automatice su flujo de trabajo utilizando integraciones para sus herramientas favoritas.'\nimage: '/img/home/explore/gem-explore-1.svg'\nto: '/deployments'\nhoverClass: 'hover:bg-sky-surface'\n---\n::\n::section-content-item\n---\ntitle: 'Módulos'\ndescription: 'Descubra nuestra lista de módulos para potenciar su proyecto Nuxt. Creado por el equipo y la comunidad de Nuxt.'\nimage: '/img/home/explore/gem-explore-2.svg'\nto: 'https://modules.nuxtjs.org'\nhoverClass: 'hover:bg-sky-surface'\n---\n::\n::section-content-item\n---\ntitle: 'Temas'\ndescription: 'Vea cómo se crea una aplicación del mundo real utilizando el stack de Nuxt con los temas creados por nuestros socios.'\nimage: '/img/home/explore/gem-explore-3.svg'\nto: '/themes'\nhoverClass: 'hover:bg-sky-surface'\n---\n::\n\n#title\n¿Avanzando? Mucho para [_Explorar_]{.text-primary}\n\n#description\nDescubra módulos potentes, intégrelos con sus proveedores favoritos y comience rápidamente con los temas.\n::\n\n::home-community\n---\ncategory: Comunidad\nannouncementsCategory: Anuncios\neventsCategory: Eventos\narticleLinkTitle: Obtener información\n---\n\n#title\nCompartir es [Demostrar interés]{.text-sky-lighter}\n\n#description\nDescubra artículos del equipo del framework y la comunidad sobre Nuxt. ¡Consejos y trucos incluidos!\n::\n\n::home-testimonials\n---\ncategory: Comunidad\n---\n#title\nTestimonios\n\n#description\nAprende lo que a los expertos les encanta de Nuxt.\n\n#testimonials\n  :::testimonials\n  ---\n  home: true\n  ---\n  :::\n::\n","ast":{"type":"root","children":[{"type":"element","tag":"home-hero","props":{},"children":[{"type":"element","tag":"template","props":{"v-slot:title":""},"children":[{"type":"element","tag":"prose-paragraph","props":{},"children":[{"type":"text","value":"El Framework de Vue"},{"type":"element","tag":"br","props":{},"children":[]},{"type":"text","value":"Intuitivo"}]}],"content":[{"type":"element","tag":"prose-paragraph","props":{},"children":[{"type":"text","value":"El Framework de Vue"},{"type":"element","tag":"br","props":{},"children":[]},{"type":"text","value":"Intuitivo"}]}]},{"type":"element","tag":"template","props":{"v-slot:description":""},"children":[{"type":"element","tag":"prose-paragraph","props":{},"children":[{"type":"text","value":"Cree su próxima aplicación Vue.js con confianza usando Nuxt."},{"type":"element","tag":"br","props":{"className":["hidden","sm:block"]},"children":[]},{"type":"text","value":" Un framework de código abierto que hace que el desarrollo web sea simple y poderoso."}]}],"content":[{"type":"element","tag":"prose-paragraph","props":{},"children":[{"type":"text","value":"Cree su próxima aplicación Vue.js con confianza usando Nuxt."},{"type":"element","tag":"br","props":{"className":["hidden","sm:block"]},"children":[]},{"type":"text","value":" Un framework de código abierto que hace que el desarrollo web sea simple y poderoso."}]}]},{"type":"element","tag":"template","props":{"v-slot:primary-button":""},"children":[{"type":"element","tag":"app-button","props":{"href":"https://github.com/nuxt/nuxt.js","extraClass":"text-white bg-sky-black hover:bg-sky-darker leading-4","icon":"IconGitHub"},"children":[{"type":"text","value":"39K+ GitHub stars"}]}],"content":[{"type":"element","tag":"app-button","props":{"href":"https://github.com/nuxt/nuxt.js","extraClass":"text-white bg-sky-black hover:bg-sky-darker leading-4","icon":"IconGitHub"},"children":[{"type":"text","value":"39K+ GitHub stars"}]}]},{"type":"element","tag":"template","props":{"v-slot:secondary-button":""},"children":[{"type":"element","tag":"app-button","props":{"to":"/docs/get-started/installation"},"children":[{"type":"text","value":"Comenzar"}]}],"content":[{"type":"element","tag":"app-button","props":{"to":"/docs/get-started/installation"},"children":[{"type":"text","value":"Comenzar"}]}]}]},{"type":"text","value":"\n"},{"type":"element","tag":"home-learn-master","props":{"category":"Aprender"},"children":[{"type":"element","tag":"template","props":{"v-slot:title":""},"children":[{"type":"element","tag":"prose-paragraph","props":{},"children":[{"type":"element","tag":"span","props":{"className":["text-primary"]},"children":[{"type":"text","value":"Fácil"}]},{"type":"text","value":" de aprender. "},{"type":"element","tag":"span","props":{"className":["text-primary"]},"children":[{"type":"text","value":"Fácil"}]},{"type":"text","value":" de dominar"}]}],"content":[{"type":"element","tag":"prose-paragraph","props":{},"children":[{"type":"element","tag":"span","props":{"className":["text-primary"]},"children":[{"type":"text","value":"Fácil"}]},{"type":"text","value":" de aprender. "},{"type":"element","tag":"span","props":{"className":["text-primary"]},"children":[{"type":"text","value":"Fácil"}]},{"type":"text","value":" de dominar"}]}]},{"type":"element","tag":"template","props":{"v-slot:description":""},"children":[{"type":"element","tag":"prose-paragraph","props":{},"children":[{"type":"text","value":"Aprende todo lo que usted necesita saber, desde principiante hasta maestro."}]}],"content":[{"type":"element","tag":"prose-paragraph","props":{},"children":[{"type":"text","value":"Aprende todo lo que usted necesita saber, desde principiante hasta maestro."}]}]},{"type":"element","tag":"template","props":{"v-slot:bottom":""},"children":[{"type":"element","tag":"app-button","props":{"to":"/docs/get-started/installation"},"children":[{"type":"text","value":"Empieza a aprender"}]}],"content":[{"type":"element","tag":"app-button","props":{"to":"/docs/get-started/installation"},"children":[{"type":"text","value":"Empieza a aprender"}]}]}]},{"type":"text","value":"\n"},{"type":"element","tag":"home-features","props":{"category":"Características"},"children":[{"type":"element","tag":"section-content-item","props":{"description":"Comience a programar su aplicación de inmediato, Nuxt se encarga del resto.","image":"/img/home/discover/dx/zero-config.svg","title":"Sin configuraciones"},"children":[]},{"type":"element","tag":"section-content-item","props":{"description":"Enrutamiento automático y división de código para cada página.","image":"/img/home/discover/dx/file-system-routing.svg","title":"Enrutamiento basado en archivos"},"children":[]},{"type":"element","tag":"section-content-item","props":{"description":"Cambie entre la generación de sitios estáticos o renderizado en el servidor bajo demanda.","image":"/img/home/discover/dx/hybrid.svg","title":"Modos de renderizado"},"children":[]},{"type":"element","tag":"section-content-item","props":{"description":"Obtenga su contenido de cualquier fuente en sus componentes de Vue, listo para SSR.","image":"/img/home/discover/dx/fetch.svg","title":"Obtención de datos"},"children":[]},{"type":"element","tag":"section-content-item","props":{"description":"Trabajo en equipo eficiente con una sólida estructura de directorios y convenciones.","image":"/img/home/discover/dx/conventions.svg","title":"Convenios fuertes"},"children":[]},{"type":"element","tag":"section-content-item","props":{"description":"Gestión de metaetiquetas y un tiempo de acceso al contenido más rápido para una excelente indexación.","image":"/img/home/discover/dx/seo.svg","title":"SEO amigable"},"children":[]},{"type":"element","tag":"section-content-item","props":{"description":"Use sus componentes, Nuxt los importará con división de código inteligente.","image":"/img/home/discover/dx/auto-inject.svg","title":"Importación automática de componentes"},"children":[]},{"type":"element","tag":"section-content-item","props":{"description":"Amplíe su aplicación con más de 160 módulos para Nuxt y cree los suyos propios.","image":"/img/home/discover/dx/modular.svg","title":"Ecosistema de módulos"},"children":[]},{"type":"element","tag":"template","props":{"v-slot:title":""},"children":[{"type":"element","tag":"prose-paragraph","props":{},"children":[{"type":"text","value":"Intuitivo "},{"type":"element","tag":"span","props":{"className":["text-primary"]},"children":[{"type":"text","value":"D"}]},{"type":"text","value":"eveloper E"},{"type":"element","tag":"span","props":{"className":["text-primary"]},"children":[{"type":"text","value":"x"}]},{"type":"text","value":"perience"}]}],"content":[{"type":"element","tag":"prose-paragraph","props":{},"children":[{"type":"text","value":"Intuitivo "},{"type":"element","tag":"span","props":{"className":["text-primary"]},"children":[{"type":"text","value":"D"}]},{"type":"text","value":"eveloper E"},{"type":"element","tag":"span","props":{"className":["text-primary"]},"children":[{"type":"text","value":"x"}]},{"type":"text","value":"perience"}]}]},{"type":"element","tag":"template","props":{"v-slot:description":""},"children":[{"type":"element","tag":"prose-paragraph","props":{},"children":[{"type":"text","value":"Nuxt se produce con muchas características para aumentar la productividad del desarrollador y la experiencia del usuario final."}]}],"content":[{"type":"element","tag":"prose-paragraph","props":{},"children":[{"type":"text","value":"Nuxt se produce con muchas características para aumentar la productividad del desarrollador y la experiencia del usuario final."}]}]}]},{"type":"text","value":"\n"},{"type":"element","tag":"home-discover-partners","props":{"category":"Partners"},"children":[{"type":"element","tag":"template","props":{"v-slot:title":""},"children":[{"type":"element","tag":"prose-paragraph","props":{},"children":[{"type":"text","value":"Desarrollo "},{"type":"element","tag":"span","props":{"className":["text-primary"]},"children":[{"type":"element","tag":"prose-em","props":{},"children":[{"type":"text","value":"Sostenible"}]}]}]}],"content":[{"type":"element","tag":"prose-paragraph","props":{},"children":[{"type":"text","value":"Desarrollo "},{"type":"element","tag":"span","props":{"className":["text-primary"]},"children":[{"type":"element","tag":"prose-em","props":{},"children":[{"type":"text","value":"Sostenible"}]}]}]}]},{"type":"element","tag":"template","props":{"v-slot:description":""},"children":[{"type":"element","tag":"prose-paragraph","props":{},"children":[{"type":"text","value":"El desarrollo de Nuxt lo llevan a cabo desarrolladores apasionados, pero la cantidad de esfuerzo necesario para mantener y desarrollar nuevas funciones no es sostenible sin el respaldo financiero adecuado. Agradecemos a nuestros patrocinadores y socios, que ayudan a hacer posible Nuxt."},{"type":"element","tag":"br","props":{},"children":[]}]}],"content":[{"type":"element","tag":"prose-paragraph","props":{},"children":[{"type":"text","value":"El desarrollo de Nuxt lo llevan a cabo desarrolladores apasionados, pero la cantidad de esfuerzo necesario para mantener y desarrollar nuevas funciones no es sostenible sin el respaldo financiero adecuado. Agradecemos a nuestros patrocinadores y socios, que ayudan a hacer posible Nuxt."},{"type":"element","tag":"br","props":{},"children":[]}]}]},{"type":"element","tag":"template","props":{"v-slot:partners-card":""},"children":[{"type":"element","tag":"home-partners-card","props":{"category":"technology","icon":"technology.svg"},"children":[{"type":"element","tag":"template","props":{"v-slot:title":""},"children":[{"type":"element","tag":"prose-paragraph","props":{},"children":[{"type":"text","value":"Technology partners"}]}],"content":[{"type":"element","tag":"prose-paragraph","props":{},"children":[{"type":"text","value":"Technology partners"}]}]},{"type":"element","tag":"template","props":{"v-slot:description":""},"children":[{"type":"element","tag":"prose-paragraph","props":{},"children":[{"type":"text","value":"Technology partners offer services that empower Nuxt developers, such as CMS, Hosting, Database, and more."}]}],"content":[{"type":"element","tag":"prose-paragraph","props":{},"children":[{"type":"text","value":"Technology partners offer services that empower Nuxt developers, such as CMS, Hosting, Database, and more."}]}]},{"type":"element","tag":"template","props":{"v-slot:button":""},"children":[{"type":"element","tag":"prose-paragraph","props":{},"children":[{"type":"text","value":"Discover our technology partners"}]}],"content":[{"type":"element","tag":"prose-paragraph","props":{},"children":[{"type":"text","value":"Discover our technology partners"}]}]}]},{"type":"element","tag":"home-partners-card","props":{"category":"agency","icon":"agency.svg"},"children":[{"type":"element","tag":"template","props":{"v-slot:title":""},"children":[{"type":"element","tag":"prose-paragraph","props":{},"children":[{"type":"text","value":"Agency partners"}]}],"content":[{"type":"element","tag":"prose-paragraph","props":{},"children":[{"type":"text","value":"Agency partners"}]}]},{"type":"element","tag":"template","props":{"v-slot:description":""},"children":[{"type":"element","tag":"prose-paragraph","props":{},"children":[{"type":"text","value":"Agency partners are trusted web and consulting agencies that can provide Nuxt development and support for your projects."}]}],"content":[{"type":"element","tag":"prose-paragraph","props":{},"children":[{"type":"text","value":"Agency partners are trusted web and consulting agencies that can provide Nuxt development and support for your projects."}]}]},{"type":"element","tag":"template","props":{"v-slot:button":""},"children":[{"type":"element","tag":"prose-paragraph","props":{},"children":[{"type":"text","value":"Find a Nuxt expert"}]}],"content":[{"type":"element","tag":"prose-paragraph","props":{},"children":[{"type":"text","value":"Find a Nuxt expert"}]}]}]}],"content":[{"type":"element","tag":"home-partners-card","props":{"category":"technology","icon":"technology.svg"},"children":[{"type":"element","tag":"template","props":{"v-slot:title":""},"children":[{"type":"element","tag":"prose-paragraph","props":{},"children":[{"type":"text","value":"Technology partners"}]}],"content":[{"type":"element","tag":"prose-paragraph","props":{},"children":[{"type":"text","value":"Technology partners"}]}]},{"type":"element","tag":"template","props":{"v-slot:description":""},"children":[{"type":"element","tag":"prose-paragraph","props":{},"children":[{"type":"text","value":"Technology partners offer services that empower Nuxt developers, such as CMS, Hosting, Database, and more."}]}],"content":[{"type":"element","tag":"prose-paragraph","props":{},"children":[{"type":"text","value":"Technology partners offer services that empower Nuxt developers, such as CMS, Hosting, Database, and more."}]}]},{"type":"element","tag":"template","props":{"v-slot:button":""},"children":[{"type":"element","tag":"prose-paragraph","props":{},"children":[{"type":"text","value":"Discover our technology partners"}]}],"content":[{"type":"element","tag":"prose-paragraph","props":{},"children":[{"type":"text","value":"Discover our technology partners"}]}]}]},{"type":"element","tag":"home-partners-card","props":{"category":"agency","icon":"agency.svg"},"children":[{"type":"element","tag":"template","props":{"v-slot:title":""},"children":[{"type":"element","tag":"prose-paragraph","props":{},"children":[{"type":"text","value":"Agency partners"}]}],"content":[{"type":"element","tag":"prose-paragraph","props":{},"children":[{"type":"text","value":"Agency partners"}]}]},{"type":"element","tag":"template","props":{"v-slot:description":""},"children":[{"type":"element","tag":"prose-paragraph","props":{},"children":[{"type":"text","value":"Agency partners are trusted web and consulting agencies that can provide Nuxt development and support for your projects."}]}],"content":[{"type":"element","tag":"prose-paragraph","props":{},"children":[{"type":"text","value":"Agency partners are trusted web and consulting agencies that can provide Nuxt development and support for your projects."}]}]},{"type":"element","tag":"template","props":{"v-slot:button":""},"children":[{"type":"element","tag":"prose-paragraph","props":{},"children":[{"type":"text","value":"Find a Nuxt expert"}]}],"content":[{"type":"element","tag":"prose-paragraph","props":{},"children":[{"type":"text","value":"Find a Nuxt expert"}]}]}]}]},{"type":"element","tag":"template","props":{"v-slot:bottom":""},"children":[{"type":"element","tag":"app-button","props":{"href":"mailto:partners@nuxtlabs.com"},"children":[{"type":"text","value":"Conviertete en un patrocinador"}]}],"content":[{"type":"element","tag":"app-button","props":{"href":"mailto:partners@nuxtlabs.com"},"children":[{"type":"text","value":"Conviertete en un patrocinador"}]}]}]},{"type":"text","value":"\n"},{"type":"element","tag":"home-learn-guides","props":{"category":"Aprender"},"children":[{"type":"element","tag":"section-content-item","props":{"description":"Descubra los conceptos de Nuxt y encuentre una referencia completa del API.","image":"/img/home/learn/guides/gem-1.svg","title":"Documentación","hoverClass":"hover:bg-sky-darker","to":"/docs/get-started/installation"},"children":[]},{"type":"element","tag":"section-content-item","props":{"description":"Aprenda con ejemplos producidos por la comunidad.","image":"/img/home/learn/guides/gem-2.svg","title":"Ejemplos","hoverClass":"hover:bg-sky-darker","to":"/examples"},"children":[]},{"type":"element","tag":"section-content-item","props":{"description":"Descubra qué ha cambiado antes de actualizar.","image":"/img/home/learn/guides/gem-3.svg","title":"Lanzamientos","hoverClass":"hover:bg-sky-darker","to":"/releases"},"children":[]},{"type":"element","tag":"section-content-item","props":{"description":"Vea una serie completa de videos para aprender Nuxt con nuestro socio Vue School.","image":"/img/home/learn/guides/gem-4.svg","title":"Cursos de Maestría","hoverClass":"hover:bg-sky-darker","to":"https://masteringnuxt.com/?utm_source=nuxt&utm_medium=link&utm_campaign=nsite"},"children":[]},{"type":"element","tag":"template","props":{"v-slot:title":""},"children":[{"type":"element","tag":"prose-paragraph","props":{},"children":[{"type":"text","value":"Sigue nuestra "},{"type":"element","tag":"span","props":{"className":["text-primary"]},"children":[{"type":"element","tag":"prose-em","props":{},"children":[{"type":"text","value":"Guías"}]}]}]}],"content":[{"type":"element","tag":"prose-paragraph","props":{},"children":[{"type":"text","value":"Sigue nuestra "},{"type":"element","tag":"span","props":{"className":["text-primary"]},"children":[{"type":"element","tag":"prose-em","props":{},"children":[{"type":"text","value":"Guías"}]}]}]}]},{"type":"element","tag":"template","props":{"v-slot:description":""},"children":[{"type":"element","tag":"prose-paragraph","props":{},"children":[{"type":"text","value":"Desde una idea hasta una obra maestra, las guías lo llevarán por el camino para convertirse en un Nuxter."}]}],"content":[{"type":"element","tag":"prose-paragraph","props":{},"children":[{"type":"text","value":"Desde una idea hasta una obra maestra, las guías lo llevarán por el camino para convertirse en un Nuxter."}]}]}]},{"type":"text","value":"\n"},{"type":"element","tag":"home-explore","props":{"category":"Explorar"},"children":[{"type":"element","tag":"section-content-item","props":{"description":"Amplíe y automatice su flujo de trabajo utilizando integraciones para sus herramientas favoritas.","image":"/img/home/explore/gem-explore-1.svg","title":"Integraciones","hoverClass":"hover:bg-sky-surface","to":"/deployments"},"children":[]},{"type":"element","tag":"section-content-item","props":{"description":"Descubra nuestra lista de módulos para potenciar su proyecto Nuxt. Creado por el equipo y la comunidad de Nuxt.","image":"/img/home/explore/gem-explore-2.svg","title":"Módulos","hoverClass":"hover:bg-sky-surface","to":"https://modules.nuxtjs.org"},"children":[]},{"type":"element","tag":"section-content-item","props":{"description":"Vea cómo se crea una aplicación del mundo real utilizando el stack de Nuxt con los temas creados por nuestros socios.","image":"/img/home/explore/gem-explore-3.svg","title":"Temas","hoverClass":"hover:bg-sky-surface","to":"/themes"},"children":[]},{"type":"element","tag":"template","props":{"v-slot:title":""},"children":[{"type":"element","tag":"prose-paragraph","props":{},"children":[{"type":"text","value":"¿Avanzando? Mucho para "},{"type":"element","tag":"span","props":{"className":["text-primary"]},"children":[{"type":"element","tag":"prose-em","props":{},"children":[{"type":"text","value":"Explorar"}]}]}]}],"content":[{"type":"element","tag":"prose-paragraph","props":{},"children":[{"type":"text","value":"¿Avanzando? Mucho para "},{"type":"element","tag":"span","props":{"className":["text-primary"]},"children":[{"type":"element","tag":"prose-em","props":{},"children":[{"type":"text","value":"Explorar"}]}]}]}]},{"type":"element","tag":"template","props":{"v-slot:description":""},"children":[{"type":"element","tag":"prose-paragraph","props":{},"children":[{"type":"text","value":"Descubra módulos potentes, intégrelos con sus proveedores favoritos y comience rápidamente con los temas."}]}],"content":[{"type":"element","tag":"prose-paragraph","props":{},"children":[{"type":"text","value":"Descubra módulos potentes, intégrelos con sus proveedores favoritos y comience rápidamente con los temas."}]}]}]},{"type":"text","value":"\n"},{"type":"element","tag":"home-community","props":{"announcementsCategory":"Anuncios","articleLinkTitle":"Obtener información","category":"Comunidad","eventsCategory":"Eventos"},"children":[{"type":"element","tag":"template","props":{"v-slot:title":""},"children":[{"type":"element","tag":"prose-paragraph","props":{},"children":[{"type":"text","value":"Compartir es "},{"type":"element","tag":"span","props":{"className":["text-sky-lighter"]},"children":[{"type":"text","value":"Demostrar interés"}]}]}],"content":[{"type":"element","tag":"prose-paragraph","props":{},"children":[{"type":"text","value":"Compartir es "},{"type":"element","tag":"span","props":{"className":["text-sky-lighter"]},"children":[{"type":"text","value":"Demostrar interés"}]}]}]},{"type":"element","tag":"template","props":{"v-slot:description":""},"children":[{"type":"element","tag":"prose-paragraph","props":{},"children":[{"type":"text","value":"Descubra artículos del equipo del framework y la comunidad sobre Nuxt. ¡Consejos y trucos incluidos!"}]}],"content":[{"type":"element","tag":"prose-paragraph","props":{},"children":[{"type":"text","value":"Descubra artículos del equipo del framework y la comunidad sobre Nuxt. ¡Consejos y trucos incluidos!"}]}]}]},{"type":"text","value":"\n"},{"type":"element","tag":"home-testimonials","props":{"category":"Comunidad"},"children":[{"type":"element","tag":"template","props":{"v-slot:title":""},"children":[{"type":"element","tag":"prose-paragraph","props":{},"children":[{"type":"text","value":"Testimonios"}]}],"content":[{"type":"element","tag":"prose-paragraph","props":{},"children":[{"type":"text","value":"Testimonios"}]}]},{"type":"element","tag":"template","props":{"v-slot:description":""},"children":[{"type":"element","tag":"prose-paragraph","props":{},"children":[{"type":"text","value":"Aprende lo que a los expertos les encanta de Nuxt."}]}],"content":[{"type":"element","tag":"prose-paragraph","props":{},"children":[{"type":"text","value":"Aprende lo que a los expertos les encanta de Nuxt."}]}]},{"type":"element","tag":"template","props":{"v-slot:testimonials":""},"children":[{"type":"element","tag":"testimonials","props":{":home":"true"},"children":[]}],"content":[{"type":"element","tag":"testimonials","props":{":home":"true"},"children":[]}]}]}]},"toc":{"title":"","searchDepth":2,"depth":2,"links":[]}}}