{"key":"content:fr:themes:index.md","generatedAt":"2022-03-15T12:18:23.462Z","mtime":"2022-03-15T12:18:23.458Z","slug":"","title":"Thèmes Nuxt","position":"999999990000","to":"/themes","draft":false,"page":true,"language":"fr","template":"blog","description":"Découvrez comment une vraie application est construite avec la stack Nuxt grâce aux thèmes édités par nos partenaires.","empty":false,"body":{"raw":"---\ntemplate: blog\ntitle: Thèmes Nuxt\ndescription: \"Découvrez comment une vraie application est construite avec la stack Nuxt grâce aux thèmes édités par nos partenaires.\"\n---\n::themes-list\n---\nthemes:\n  one:\n    title: Nuxt Argon Dashboard PRO\n    description: Le thème Nuxt Argon Dashboard PRO est constitué de plus de 200 composants, vous offrant un large choix de combinaisons.\n    image: /img/themes/argon_dashboard_pro.jpg\n    slug: one\n    price: $99\n    href: https://www.creative-tim.com/product/nuxt-argon-dashboard-pro?partner=120213\n  two:\n    title: Nuxt Argon Dashboard PRO Laravel\n    description: \"Toutes les fonctionnalités d'un CMS léger et prêt à l'emploi, tirant partie de deux frameworks populaires et modernes: Nuxt et Laravel.\"\n    image: /img/themes/argon_dashboard_pro_laravel.jpg\n    slug: two\n    price: $149\n    href: https://www.creative-tim.com/product/nuxt-argon-dashboard-pro-laravel?partner=120213\n  three:\n    title: Nuxt Now UI Kit\n    description: Un kit premium responsive basé sur Bootstrap 4, conçu par Invision et Creative Tim. Ce beau kit UI cross-platform comprend plus de 1000 éléments et 11 templates.\n    image: /img/themes/nuxt_now_ui_kit.jpg\n    slug: three\n    price: $89\n    href: https://www.creative-tim.com/product/nuxt-now-ui-kit-pro?partner=120213\n  four:\n    title: Nuxt Black Dashboard PRO\n    description: \"Un beau tableau de bord Bootstrap 4 livré en 2 versions: Mode Light et Dark.\"\n    image: /img/themes/nuxt_black_dashboard_pro.jpg\n    slug: four\n    price: $79\n    href: https://www.creative-tim.com/product/nuxt-black-dashboard-pro?partner=120213\n  five:\n    title: Nuxt Scutum Dashboard\n    description: Scutum Admin est un template Material Design professionel en HTML5/CSS3, basé sur UIkit Framework (v3) et Nuxt.\n    image: /img/themes/scutum_dashboard.jpg\n    slug: five\n    price: $26\n    href: https://1.envato.market/scutum-nuxt\n---\n::\n","ast":{"type":"root","children":[{"type":"element","tag":"themes-list","props":{":themes":"{\"one\":{\"title\":\"Nuxt Argon Dashboard PRO\",\"description\":\"Le thème Nuxt Argon Dashboard PRO est constitué de plus de 200 composants, vous offrant un large choix de combinaisons.\",\"image\":\"/img/themes/argon_dashboard_pro.jpg\",\"slug\":\"one\",\"price\":\"$99\",\"href\":\"https://www.creative-tim.com/product/nuxt-argon-dashboard-pro?partner=120213\"},\"two\":{\"title\":\"Nuxt Argon Dashboard PRO Laravel\",\"description\":\"Toutes les fonctionnalités d'un CMS léger et prêt à l'emploi, tirant partie de deux frameworks populaires et modernes: Nuxt et Laravel.\",\"image\":\"/img/themes/argon_dashboard_pro_laravel.jpg\",\"slug\":\"two\",\"price\":\"$149\",\"href\":\"https://www.creative-tim.com/product/nuxt-argon-dashboard-pro-laravel?partner=120213\"},\"three\":{\"title\":\"Nuxt Now UI Kit\",\"description\":\"Un kit premium responsive basé sur Bootstrap 4, conçu par Invision et Creative Tim. Ce beau kit UI cross-platform comprend plus de 1000 éléments et 11 templates.\",\"image\":\"/img/themes/nuxt_now_ui_kit.jpg\",\"slug\":\"three\",\"price\":\"$89\",\"href\":\"https://www.creative-tim.com/product/nuxt-now-ui-kit-pro?partner=120213\"},\"four\":{\"title\":\"Nuxt Black Dashboard PRO\",\"description\":\"Un beau tableau de bord Bootstrap 4 livré en 2 versions: Mode Light et Dark.\",\"image\":\"/img/themes/nuxt_black_dashboard_pro.jpg\",\"slug\":\"four\",\"price\":\"$79\",\"href\":\"https://www.creative-tim.com/product/nuxt-black-dashboard-pro?partner=120213\"},\"five\":{\"title\":\"Nuxt Scutum Dashboard\",\"description\":\"Scutum Admin est un template Material Design professionel en HTML5/CSS3, basé sur UIkit Framework (v3) et Nuxt.\",\"image\":\"/img/themes/scutum_dashboard.jpg\",\"slug\":\"five\",\"price\":\"$26\",\"href\":\"https://1.envato.market/scutum-nuxt\"}}"},"children":[]}]},"toc":{"title":"","searchDepth":2,"depth":2,"links":[]}}}