{"key":"content:ja:themes:index.md","generatedAt":"2022-03-15T12:42:48.185Z","mtime":"2022-03-15T12:42:48.181Z","slug":"","title":"Nuxt テーマ","position":"999999990000","to":"/themes","draft":false,"page":true,"language":"ja","template":"blog","description":"パートナーが構築したテーマを使って、Nuxtを使った実際のアプリケーションがどのように構築されているかをご覧ください。","empty":false,"body":{"raw":"---\ntemplate: blog\ntitle: Nuxt テーマ\ndescription: \"パートナーが構築したテーマを使って、Nuxtを使った実際のアプリケーションがどのように構築されているかをご覧ください。\"\n---\n\n::themes-list\n---\nthemes:\n  one:\n    title: Nuxt Argon Dashboard PRO\n    description: Nuxt Argon Dashboard PRO は、200 以上の独立したコンポーネントで構成されており、自由に選択して組み合わせることができます。\n    image: /img/themes/argon_dashboard_pro.jpg\n    slug: one\n    price: $99\n    href: https://www.creative-tim.com/product/nuxt-argon-dashboard-pro?partner=120213\n  two:\n    title: Nuxt Argon Dashboard PRO Laravel\n    description: 現在最も人気のある Nuxt と Laravel 2つのフレームワークを使用して構築された、軽量なCMSの機能をすべて備えています。\n    image: /img/themes/argon_dashboard_pro_laravel.jpg\n    slug: two\n    price: $149\n    href: https://www.creative-tim.com/product/nuxt-argon-dashboard-pro-laravel?partner=120213\n  three:\n    title: Nuxt Now UI Kit\n    description: Invision と Creative Tim が提供するプレミアムレスポンシブ Bootstrap 4 Kit です。1000 以上の要素と 11 のテンプレートを備えた、美しいクロスプラットフォームの UI Kit です。\n    image: /img/themes/nuxt_now_ui_kit.jpg\n    slug: three\n    price: $89\n    href: https://www.creative-tim.com/product/nuxt-now-ui-kit-pro?partner=120213\n  four:\n    title: Nuxt Black Dashboard PRO\n    description: 2つのバージョンがある美しい Bootstrap 4 管理者ダッシュボードです。ダークモードとライトモードの2種類があります。\n    image: /img/themes/nuxt_black_dashboard_pro.jpg\n    slug: four\n    price: $79\n    href: https://www.creative-tim.com/product/nuxt-black-dashboard-pro?partner=120213\n  five:\n    title: Nuxt Scutum Dashboard\n    description: Scutum Admin は、UIkit Framework (v3) と Nuxt をベースにした、プロフェッショナルな HTML5 / CSS3 Material Design テンプレートです。\n    image: /img/themes/scutum_dashboard.jpg\n    slug: five\n    price: $26\n    href: https://1.envato.market/scutum-nuxt\n---\n::\n","ast":{"type":"root","children":[{"type":"element","tag":"themes-list","props":{":themes":"{\"one\":{\"title\":\"Nuxt Argon Dashboard PRO\",\"description\":\"Nuxt Argon Dashboard PRO は、200 以上の独立したコンポーネントで構成されており、自由に選択して組み合わせることができます。\",\"image\":\"/img/themes/argon_dashboard_pro.jpg\",\"slug\":\"one\",\"price\":\"$99\",\"href\":\"https://www.creative-tim.com/product/nuxt-argon-dashboard-pro?partner=120213\"},\"two\":{\"title\":\"Nuxt Argon Dashboard PRO Laravel\",\"description\":\"現在最も人気のある Nuxt と Laravel 2つのフレームワークを使用して構築された、軽量なCMSの機能をすべて備えています。\",\"image\":\"/img/themes/argon_dashboard_pro_laravel.jpg\",\"slug\":\"two\",\"price\":\"$149\",\"href\":\"https://www.creative-tim.com/product/nuxt-argon-dashboard-pro-laravel?partner=120213\"},\"three\":{\"title\":\"Nuxt Now UI Kit\",\"description\":\"Invision と Creative Tim が提供するプレミアムレスポンシブ Bootstrap 4 Kit です。1000 以上の要素と 11 のテンプレートを備えた、美しいクロスプラットフォームの UI Kit です。\",\"image\":\"/img/themes/nuxt_now_ui_kit.jpg\",\"slug\":\"three\",\"price\":\"$89\",\"href\":\"https://www.creative-tim.com/product/nuxt-now-ui-kit-pro?partner=120213\"},\"four\":{\"title\":\"Nuxt Black Dashboard PRO\",\"description\":\"2つのバージョンがある美しい Bootstrap 4 管理者ダッシュボードです。ダークモードとライトモードの2種類があります。\",\"image\":\"/img/themes/nuxt_black_dashboard_pro.jpg\",\"slug\":\"four\",\"price\":\"$79\",\"href\":\"https://www.creative-tim.com/product/nuxt-black-dashboard-pro?partner=120213\"},\"five\":{\"title\":\"Nuxt Scutum Dashboard\",\"description\":\"Scutum Admin は、UIkit Framework (v3) と Nuxt をベースにした、プロフェッショナルな HTML5 / CSS3 Material Design テンプレートです。\",\"image\":\"/img/themes/scutum_dashboard.jpg\",\"slug\":\"five\",\"price\":\"$26\",\"href\":\"https://1.envato.market/scutum-nuxt\"}}"},"children":[]}]},"toc":{"title":"","searchDepth":2,"depth":2,"links":[]}}}