{"key":"content:pt-br:index.md","generatedAt":"2022-03-15T12:42:51.983Z","mtime":"2022-03-15T12:42:51.959Z","slug":"","title":"O Framework Intuitivo do Vue","position":"999999990000","to":"/pt-br","draft":false,"page":true,"language":"en","template":"blank","description":"Construa sua próxima aplicação Vue.js com confiança usando Nuxt. Um framework de código aberto que torna o desenvolvimento web simples e poderoso.","bgClass":"bg-white","empty":false,"body":{"raw":"---\ntemplate: blank\ntitle: 'O Framework Intuitivo do Vue'\ndescription: 'Construa sua próxima aplicação Vue.js com confiança usando Nuxt. Um framework de código aberto que torna o desenvolvimento web simples e poderoso.'\nbgClass: 'bg-white'\n---\n\n::home-hero\n#title\nO Framework<br>Intuitivo do Vue\n\n#description\nConstrua sua próxima aplicação Vue.js com confiança usando Nuxt.<br class=\"hideen sm:block\" /> Um framework de código aberto que torna o desenvolvimento web simples e poderoso.\n\n#primary-button\n:app-button[39K+ estrelas no GitHub]{ href=\"https://github.com/nuxt/nuxt.js\" icon=\"IconGitHub\" extraClass=\"text-white bg-sky-black hover:bg-sky-darker leading-4\" }\n\n#secondary-button\n:app-button[Comece a usar]{ to=\"/docs/get-started/installation\" extraClass=\"text-black bg-primary-500 hover:bg-primary-400 focus:ring-primary-600 py-4\" }\n::\n\n::home-learn-master\n---\ncategory: Aprenda\n---\n\n#title\n[Fácil]{.text-primary} de aprender. [Fácil]{.text-primary} de dominar\n\n#description\nAprenda tudo o que você precisa saber, do iniciante ao mestre.\n\n#bottom\n:app-button[Comece a aprender]{to=\"/docs/get-started/installation\"}\n::\n\n::home-features\n---\ncategory: Características\n---\n\n::section-content-item\n---\ntitle: Configuração Zero\ndescription: 'Comece a escrever seu aplicativo imediatamente, o Nuxt se encarrega do resto.'\nimage: /img/home/discover/dx/zero-config.svg\n---\n::\n\n::section-content-item\n---\ntitle: Sistema Arquivos-Rotas\ndescription: 'Roteamento automático e divisão de código para cada página.'\nimage: /img/home/discover/dx/file-system-routing.svg\n---\n::\n\n::section-content-item\n---\ntitle: Modos de Renderização\ndescription: 'Alterne entre a geração estática ou a renderização do servidor sob demanda.'\nimage: /img/home/discover/dx/hybrid.svg\n---\n::\n\n::section-content-item\n---\ntitle: Obtenção de Dados\ndescription: 'Obtenha seu conteúdo de qualquer fonte em seus componentes Vue, SSR pronto.'\nimage: /img/home/discover/dx/fetch.svg\n---\n::\n\n::section-content-item\n---\ntitle: Trabalho em Equipe Simples\ndescription: 'Trabalho em equipe eficiente com uma forte estrutura de diretórios e convenções.'\nimage: /img/home/discover/dx/conventions.svg\n---\n::\n\n::section-content-item\n---\ntitle: SEO Amigável\ndescription: 'Gerenciamento de meta tags e tempo mais rápido para uma grande indexação.'\nimage: /img/home/discover/dx/seo.svg\n---\n::\n\n::section-content-item\n---\ntitle: Auto-importação de Componentes\ndescription: 'Apenas use seus componentes, Nuxt os importará com divisão inteligente do código.'\nimage: /img/home/discover/dx/auto-inject.svg\n---\n::\n\n::section-content-item\n---\ntitle: Ecossistema de Módulos\ndescription: 'Amplie seu aplicativo com 160+ módulos Nuxt e crie o seu próprio.'\nimage: /img/home/discover/dx/modular.svg\n---\n::\n\n#title\nE[x]{.text-primary}periência Intuitiva do [D]{.text-primary}esenvolvedor\n\n#description\nNuxt é fornecido com muitas características para aumentar a produtividade do desenvolvedor e a experiência do usuário final.\n::\n\n::home-discover-partners\n---\ncategory: Parceiros\n---\n\n#title\n[_Desenvolvimento_]{.text-primary} Sustentável\n\n#description\nO desenvolvimento do Nuxt é realizado por desenvolvedores apaixonados, mas a quantidade de esforço necessária para manter e desenvolver novas características não é sustentável sem o apoio financeiro adequado. Estamos gratos por nossos patrocinadores e parceiros, que ajudam a tornar possível o Nuxt.<br>\n\n#partners-card\n  ::home-partners-card\n  ---\n  icon: technology.svg\n  category: technology\n  ---\n  #title\n  Parceiros de Tecnologia\n\n  #description\n  Os Parceiros de Tecnologia oferecem serviços que capacitam os desenvolvedores Nuxt, tais como CMS, Hospedagem, Banco de dados e mais.\n\n  #button\n  Descubra nosso parceiros de tecnologia\n  ::\n\n  ::home-partners-card\n  ---\n  icon: agency.svg\n  category: agency\n  ---\n  #title\n  Parceiros de Agências\n\n  #description\n  Os Parceiros de Agências são agências de consultoria e web de confiança que podem fornecer desenvolvimento e suporte ao Nuxt nos seus projetos.\n\n  #button\n  Encontre um especialista Nuxt\n  ::\n\n#bottom\n  :app-button[Seja Parceiro]{href=\"mailto:partners@nuxtlabs.com\"}\n::\n\n::home-learn-guides\n---\ncategory: Aprenda\n---\n\n::section-content-item\n---\ntitle: Documentação\ndescription: 'Descubra os conceitos Nuxt e encontre uma referência completa para a API.'\nimage: /img/home/learn/guides/gem-1.svg\nto: '/docs/get-started/installation'\nhoverClass: 'hover:bg-sky-darker'\n---\n::\n\n::section-content-item\n---\ntitle: Exemplos\ndescription: 'Aprenda com exemplos criados pela comunidade.'\nimage: /img/home/learn/guides/gem-2.svg\nto: '/examples'\nhoverClass: 'hover:bg-sky-darker'\n---\n::\n\n::section-content-item\n---\ntitle: Lançamentos\ndescription: 'Veja o que foi modificando antes de atualizar.'\nimage: /img/home/learn/guides/gem-3.svg\nto: '/releases'\nhoverClass: 'hover:bg-sky-darker'\n---\n::\n\n::section-content-item\n---\ntitle: Cursos de Mestres\ndescription: 'Assista uma série completa de vídeos para aprender Nuxt com nossos parceiros Vue School.'\nimage: /img/home/learn/guides/gem-4.svg\nto: 'https://masteringnuxt.com/?utm_source=nuxt&utm_medium=link&utm_campaign=nsite'\nhoverClass: 'hover:bg-sky-darker'\n---\n::\n\n#title\nSiga nossos [_Guias_]{.text-primary}\n\n#description\nDe uma idéia a uma obra-prima, guias levam você ao caminho para ser um Nuxter.\n::\n\n::home-explore\n---\ncategory: Explore\n---\n\n::section-content-item\n---\ntitle: 'Deploy'\ndescription: 'Amplie e automatize o seu fluxo de trabalho usando deploys para suas ferramentas favoritas.'\nimage: '/img/home/explore/gem-explore-1.svg'\nto: '/deployments'\nhoverClass: 'hover:bg-sky-surface'\n---\n::\n::section-content-item\n---\ntitle: 'Módulos'\ndescription: 'Descubra nossa lista de módulos para dar super-poderes ao seu projeto Nuxt. Criado pelo time do Nuxt e pela comunidade.'\nimage: '/img/home/explore/gem-explore-2.svg'\nto: 'https://modules.nuxtjs.org'\nhoverClass: 'hover:bg-sky-surface'\n---\n::\n::section-content-item\n---\ntitle: 'Temas'\ndescription: 'Veja como uma aplicação real é construída usando Nuxt com temas feitos pelos nossos parceiros.'\nimage: '/img/home/explore/gem-explore-3.svg'\nto: '/themes'\nhoverClass: 'hover:bg-sky-surface'\n---\n::\n\n#title\nSeguindo em frente? Ainda têm muito pra [_Explorar_]{.text-primary}\n\n#description\nDescubra módulos poderosos, integre-se com os seus provedores favoritos e comece rápido com os temas.\n::\n\n::home-community\n---\ncategory: Comunidade\nannouncementsCategory: Anúncios\neventsCategory: Eventos\narticleLinkTitle: Saiba mais\n---\n\n#title\nCompartilhar é [Cuidar]{.text-sky-lighter}\n\n#description\nDescubra artigos da equipe de estrutura e da comunidade sobre Nuxt. Dicas e truques incluídos!\n::\n\n::home-testimonials\n---\ncategory: Comunidade\n---\n#title\nDepoimentos\n\n#description\nVeja o que o especialistas adoram no Nuxt.\n\n#testimonials\n  :::testimonials\n  ---\n  home: true\n  ---\n  :::\n::\n","ast":{"type":"root","children":[{"type":"element","tag":"home-hero","props":{},"children":[{"type":"element","tag":"template","props":{"v-slot:title":""},"children":[{"type":"element","tag":"prose-paragraph","props":{},"children":[{"type":"text","value":"O Framework"},{"type":"element","tag":"br","props":{},"children":[]},{"type":"text","value":"Intuitivo do Vue"}]}],"content":[{"type":"element","tag":"prose-paragraph","props":{},"children":[{"type":"text","value":"O Framework"},{"type":"element","tag":"br","props":{},"children":[]},{"type":"text","value":"Intuitivo do Vue"}]}]},{"type":"element","tag":"template","props":{"v-slot:description":""},"children":[{"type":"element","tag":"prose-paragraph","props":{},"children":[{"type":"text","value":"Construa sua próxima aplicação Vue.js com confiança usando Nuxt."},{"type":"element","tag":"br","props":{"className":["hideen","sm:block"]},"children":[]},{"type":"text","value":" Um framework de código aberto que torna o desenvolvimento web simples e poderoso."}]}],"content":[{"type":"element","tag":"prose-paragraph","props":{},"children":[{"type":"text","value":"Construa sua próxima aplicação Vue.js com confiança usando Nuxt."},{"type":"element","tag":"br","props":{"className":["hideen","sm:block"]},"children":[]},{"type":"text","value":" Um framework de código aberto que torna o desenvolvimento web simples e poderoso."}]}]},{"type":"element","tag":"template","props":{"v-slot:primary-button":""},"children":[{"type":"element","tag":"app-button","props":{"extraClass":"text-white bg-sky-black hover:bg-sky-darker leading-4","href":"https://github.com/nuxt/nuxt.js","icon":"IconGitHub"},"children":[{"type":"text","value":"39K+ estrelas no GitHub"}]}],"content":[{"type":"element","tag":"app-button","props":{"extraClass":"text-white bg-sky-black hover:bg-sky-darker leading-4","href":"https://github.com/nuxt/nuxt.js","icon":"IconGitHub"},"children":[{"type":"text","value":"39K+ estrelas no GitHub"}]}]},{"type":"element","tag":"template","props":{"v-slot:secondary-button":""},"children":[{"type":"element","tag":"app-button","props":{"extraClass":"text-black bg-primary-500 hover:bg-primary-400 focus:ring-primary-600 py-4","to":"/docs/get-started/installation"},"children":[{"type":"text","value":"Comece a usar"}]}],"content":[{"type":"element","tag":"app-button","props":{"extraClass":"text-black bg-primary-500 hover:bg-primary-400 focus:ring-primary-600 py-4","to":"/docs/get-started/installation"},"children":[{"type":"text","value":"Comece a usar"}]}]}]},{"type":"text","value":"\n"},{"type":"element","tag":"home-learn-master","props":{"category":"Aprenda"},"children":[{"type":"element","tag":"template","props":{"v-slot:title":""},"children":[{"type":"element","tag":"prose-paragraph","props":{},"children":[{"type":"element","tag":"span","props":{"className":["text-primary"]},"children":[{"type":"text","value":"Fácil"}]},{"type":"text","value":" de aprender. "},{"type":"element","tag":"span","props":{"className":["text-primary"]},"children":[{"type":"text","value":"Fácil"}]},{"type":"text","value":" de dominar"}]}],"content":[{"type":"element","tag":"prose-paragraph","props":{},"children":[{"type":"element","tag":"span","props":{"className":["text-primary"]},"children":[{"type":"text","value":"Fácil"}]},{"type":"text","value":" de aprender. "},{"type":"element","tag":"span","props":{"className":["text-primary"]},"children":[{"type":"text","value":"Fácil"}]},{"type":"text","value":" de dominar"}]}]},{"type":"element","tag":"template","props":{"v-slot:description":""},"children":[{"type":"element","tag":"prose-paragraph","props":{},"children":[{"type":"text","value":"Aprenda tudo o que você precisa saber, do iniciante ao mestre."}]}],"content":[{"type":"element","tag":"prose-paragraph","props":{},"children":[{"type":"text","value":"Aprenda tudo o que você precisa saber, do iniciante ao mestre."}]}]},{"type":"element","tag":"template","props":{"v-slot:bottom":""},"children":[{"type":"element","tag":"app-button","props":{"to":"/docs/get-started/installation"},"children":[{"type":"text","value":"Comece a aprender"}]}],"content":[{"type":"element","tag":"app-button","props":{"to":"/docs/get-started/installation"},"children":[{"type":"text","value":"Comece a aprender"}]}]}]},{"type":"text","value":"\n"},{"type":"element","tag":"home-features","props":{"category":"Características"},"children":[{"type":"element","tag":"section-content-item","props":{"description":"Comece a escrever seu aplicativo imediatamente, o Nuxt se encarrega do resto.","image":"/img/home/discover/dx/zero-config.svg","title":"Configuração Zero"},"children":[]},{"type":"element","tag":"section-content-item","props":{"description":"Roteamento automático e divisão de código para cada página.","image":"/img/home/discover/dx/file-system-routing.svg","title":"Sistema Arquivos-Rotas"},"children":[]},{"type":"element","tag":"section-content-item","props":{"description":"Alterne entre a geração estática ou a renderização do servidor sob demanda.","image":"/img/home/discover/dx/hybrid.svg","title":"Modos de Renderização"},"children":[]},{"type":"element","tag":"section-content-item","props":{"description":"Obtenha seu conteúdo de qualquer fonte em seus componentes Vue, SSR pronto.","image":"/img/home/discover/dx/fetch.svg","title":"Obtenção de Dados"},"children":[]},{"type":"element","tag":"section-content-item","props":{"description":"Trabalho em equipe eficiente com uma forte estrutura de diretórios e convenções.","image":"/img/home/discover/dx/conventions.svg","title":"Trabalho em Equipe Simples"},"children":[]},{"type":"element","tag":"section-content-item","props":{"description":"Gerenciamento de meta tags e tempo mais rápido para uma grande indexação.","image":"/img/home/discover/dx/seo.svg","title":"SEO Amigável"},"children":[]},{"type":"element","tag":"section-content-item","props":{"description":"Apenas use seus componentes, Nuxt os importará com divisão inteligente do código.","image":"/img/home/discover/dx/auto-inject.svg","title":"Auto-importação de Componentes"},"children":[]},{"type":"element","tag":"section-content-item","props":{"description":"Amplie seu aplicativo com 160+ módulos Nuxt e crie o seu próprio.","image":"/img/home/discover/dx/modular.svg","title":"Ecossistema de Módulos"},"children":[]},{"type":"element","tag":"template","props":{"v-slot:title":""},"children":[{"type":"element","tag":"prose-paragraph","props":{},"children":[{"type":"text","value":"E"},{"type":"element","tag":"span","props":{"className":["text-primary"]},"children":[{"type":"text","value":"x"}]},{"type":"text","value":"periência Intuitiva do "},{"type":"element","tag":"span","props":{"className":["text-primary"]},"children":[{"type":"text","value":"D"}]},{"type":"text","value":"esenvolvedor"}]}],"content":[{"type":"element","tag":"prose-paragraph","props":{},"children":[{"type":"text","value":"E"},{"type":"element","tag":"span","props":{"className":["text-primary"]},"children":[{"type":"text","value":"x"}]},{"type":"text","value":"periência Intuitiva do "},{"type":"element","tag":"span","props":{"className":["text-primary"]},"children":[{"type":"text","value":"D"}]},{"type":"text","value":"esenvolvedor"}]}]},{"type":"element","tag":"template","props":{"v-slot:description":""},"children":[{"type":"element","tag":"prose-paragraph","props":{},"children":[{"type":"text","value":"Nuxt é fornecido com muitas características para aumentar a produtividade do desenvolvedor e a experiência do usuário final."}]}],"content":[{"type":"element","tag":"prose-paragraph","props":{},"children":[{"type":"text","value":"Nuxt é fornecido com muitas características para aumentar a produtividade do desenvolvedor e a experiência do usuário final."}]}]}]},{"type":"text","value":"\n"},{"type":"element","tag":"home-discover-partners","props":{"category":"Parceiros"},"children":[{"type":"element","tag":"template","props":{"v-slot:title":""},"children":[{"type":"element","tag":"prose-paragraph","props":{},"children":[{"type":"element","tag":"span","props":{"className":["text-primary"]},"children":[{"type":"element","tag":"prose-em","props":{},"children":[{"type":"text","value":"Desenvolvimento"}]}]},{"type":"text","value":" Sustentável"}]}],"content":[{"type":"element","tag":"prose-paragraph","props":{},"children":[{"type":"element","tag":"span","props":{"className":["text-primary"]},"children":[{"type":"element","tag":"prose-em","props":{},"children":[{"type":"text","value":"Desenvolvimento"}]}]},{"type":"text","value":" Sustentável"}]}]},{"type":"element","tag":"template","props":{"v-slot:description":""},"children":[{"type":"element","tag":"prose-paragraph","props":{},"children":[{"type":"text","value":"O desenvolvimento do Nuxt é realizado por desenvolvedores apaixonados, mas a quantidade de esforço necessária para manter e desenvolver novas características não é sustentável sem o apoio financeiro adequado. Estamos gratos por nossos patrocinadores e parceiros, que ajudam a tornar possível o Nuxt."},{"type":"element","tag":"br","props":{},"children":[]}]}],"content":[{"type":"element","tag":"prose-paragraph","props":{},"children":[{"type":"text","value":"O desenvolvimento do Nuxt é realizado por desenvolvedores apaixonados, mas a quantidade de esforço necessária para manter e desenvolver novas características não é sustentável sem o apoio financeiro adequado. Estamos gratos por nossos patrocinadores e parceiros, que ajudam a tornar possível o Nuxt."},{"type":"element","tag":"br","props":{},"children":[]}]}]},{"type":"element","tag":"template","props":{"v-slot:partners-card":""},"children":[{"type":"element","tag":"home-partners-card","props":{"category":"technology","icon":"technology.svg"},"children":[{"type":"element","tag":"template","props":{"v-slot:title":""},"children":[{"type":"element","tag":"prose-paragraph","props":{},"children":[{"type":"text","value":"Parceiros de Tecnologia"}]}],"content":[{"type":"element","tag":"prose-paragraph","props":{},"children":[{"type":"text","value":"Parceiros de Tecnologia"}]}]},{"type":"element","tag":"template","props":{"v-slot:description":""},"children":[{"type":"element","tag":"prose-paragraph","props":{},"children":[{"type":"text","value":"Os Parceiros de Tecnologia oferecem serviços que capacitam os desenvolvedores Nuxt, tais como CMS, Hospedagem, Banco de dados e mais."}]}],"content":[{"type":"element","tag":"prose-paragraph","props":{},"children":[{"type":"text","value":"Os Parceiros de Tecnologia oferecem serviços que capacitam os desenvolvedores Nuxt, tais como CMS, Hospedagem, Banco de dados e mais."}]}]},{"type":"element","tag":"template","props":{"v-slot:button":""},"children":[{"type":"element","tag":"prose-paragraph","props":{},"children":[{"type":"text","value":"Descubra nosso parceiros de tecnologia"}]}],"content":[{"type":"element","tag":"prose-paragraph","props":{},"children":[{"type":"text","value":"Descubra nosso parceiros de tecnologia"}]}]}]},{"type":"element","tag":"home-partners-card","props":{"category":"agency","icon":"agency.svg"},"children":[{"type":"element","tag":"template","props":{"v-slot:title":""},"children":[{"type":"element","tag":"prose-paragraph","props":{},"children":[{"type":"text","value":"Parceiros de Agências"}]}],"content":[{"type":"element","tag":"prose-paragraph","props":{},"children":[{"type":"text","value":"Parceiros de Agências"}]}]},{"type":"element","tag":"template","props":{"v-slot:description":""},"children":[{"type":"element","tag":"prose-paragraph","props":{},"children":[{"type":"text","value":"Os Parceiros de Agências são agências de consultoria e web de confiança que podem fornecer desenvolvimento e suporte ao Nuxt nos seus projetos."}]}],"content":[{"type":"element","tag":"prose-paragraph","props":{},"children":[{"type":"text","value":"Os Parceiros de Agências são agências de consultoria e web de confiança que podem fornecer desenvolvimento e suporte ao Nuxt nos seus projetos."}]}]},{"type":"element","tag":"template","props":{"v-slot:button":""},"children":[{"type":"element","tag":"prose-paragraph","props":{},"children":[{"type":"text","value":"Encontre um especialista Nuxt"}]}],"content":[{"type":"element","tag":"prose-paragraph","props":{},"children":[{"type":"text","value":"Encontre um especialista Nuxt"}]}]}]}],"content":[{"type":"element","tag":"home-partners-card","props":{"category":"technology","icon":"technology.svg"},"children":[{"type":"element","tag":"template","props":{"v-slot:title":""},"children":[{"type":"element","tag":"prose-paragraph","props":{},"children":[{"type":"text","value":"Parceiros de Tecnologia"}]}],"content":[{"type":"element","tag":"prose-paragraph","props":{},"children":[{"type":"text","value":"Parceiros de Tecnologia"}]}]},{"type":"element","tag":"template","props":{"v-slot:description":""},"children":[{"type":"element","tag":"prose-paragraph","props":{},"children":[{"type":"text","value":"Os Parceiros de Tecnologia oferecem serviços que capacitam os desenvolvedores Nuxt, tais como CMS, Hospedagem, Banco de dados e mais."}]}],"content":[{"type":"element","tag":"prose-paragraph","props":{},"children":[{"type":"text","value":"Os Parceiros de Tecnologia oferecem serviços que capacitam os desenvolvedores Nuxt, tais como CMS, Hospedagem, Banco de dados e mais."}]}]},{"type":"element","tag":"template","props":{"v-slot:button":""},"children":[{"type":"element","tag":"prose-paragraph","props":{},"children":[{"type":"text","value":"Descubra nosso parceiros de tecnologia"}]}],"content":[{"type":"element","tag":"prose-paragraph","props":{},"children":[{"type":"text","value":"Descubra nosso parceiros de tecnologia"}]}]}]},{"type":"element","tag":"home-partners-card","props":{"category":"agency","icon":"agency.svg"},"children":[{"type":"element","tag":"template","props":{"v-slot:title":""},"children":[{"type":"element","tag":"prose-paragraph","props":{},"children":[{"type":"text","value":"Parceiros de Agências"}]}],"content":[{"type":"element","tag":"prose-paragraph","props":{},"children":[{"type":"text","value":"Parceiros de Agências"}]}]},{"type":"element","tag":"template","props":{"v-slot:description":""},"children":[{"type":"element","tag":"prose-paragraph","props":{},"children":[{"type":"text","value":"Os Parceiros de Agências são agências de consultoria e web de confiança que podem fornecer desenvolvimento e suporte ao Nuxt nos seus projetos."}]}],"content":[{"type":"element","tag":"prose-paragraph","props":{},"children":[{"type":"text","value":"Os Parceiros de Agências são agências de consultoria e web de confiança que podem fornecer desenvolvimento e suporte ao Nuxt nos seus projetos."}]}]},{"type":"element","tag":"template","props":{"v-slot:button":""},"children":[{"type":"element","tag":"prose-paragraph","props":{},"children":[{"type":"text","value":"Encontre um especialista Nuxt"}]}],"content":[{"type":"element","tag":"prose-paragraph","props":{},"children":[{"type":"text","value":"Encontre um especialista Nuxt"}]}]}]}]},{"type":"element","tag":"template","props":{"v-slot:bottom":""},"children":[{"type":"element","tag":"app-button","props":{"href":"mailto:partners@nuxtlabs.com"},"children":[{"type":"text","value":"Seja Parceiro"}]}],"content":[{"type":"element","tag":"app-button","props":{"href":"mailto:partners@nuxtlabs.com"},"children":[{"type":"text","value":"Seja Parceiro"}]}]}]},{"type":"text","value":"\n"},{"type":"element","tag":"home-learn-guides","props":{"category":"Aprenda"},"children":[{"type":"element","tag":"section-content-item","props":{"description":"Descubra os conceitos Nuxt e encontre uma referência completa para a API.","image":"/img/home/learn/guides/gem-1.svg","title":"Documentação","hoverClass":"hover:bg-sky-darker","to":"/docs/get-started/installation"},"children":[]},{"type":"element","tag":"section-content-item","props":{"description":"Aprenda com exemplos criados pela comunidade.","image":"/img/home/learn/guides/gem-2.svg","title":"Exemplos","hoverClass":"hover:bg-sky-darker","to":"/examples"},"children":[]},{"type":"element","tag":"section-content-item","props":{"description":"Veja o que foi modificando antes de atualizar.","image":"/img/home/learn/guides/gem-3.svg","title":"Lançamentos","hoverClass":"hover:bg-sky-darker","to":"/releases"},"children":[]},{"type":"element","tag":"section-content-item","props":{"description":"Assista uma série completa de vídeos para aprender Nuxt com nossos parceiros Vue School.","image":"/img/home/learn/guides/gem-4.svg","title":"Cursos de Mestres","hoverClass":"hover:bg-sky-darker","to":"https://masteringnuxt.com/?utm_source=nuxt&utm_medium=link&utm_campaign=nsite"},"children":[]},{"type":"element","tag":"template","props":{"v-slot:title":""},"children":[{"type":"element","tag":"prose-paragraph","props":{},"children":[{"type":"text","value":"Siga nossos "},{"type":"element","tag":"span","props":{"className":["text-primary"]},"children":[{"type":"element","tag":"prose-em","props":{},"children":[{"type":"text","value":"Guias"}]}]}]}],"content":[{"type":"element","tag":"prose-paragraph","props":{},"children":[{"type":"text","value":"Siga nossos "},{"type":"element","tag":"span","props":{"className":["text-primary"]},"children":[{"type":"element","tag":"prose-em","props":{},"children":[{"type":"text","value":"Guias"}]}]}]}]},{"type":"element","tag":"template","props":{"v-slot:description":""},"children":[{"type":"element","tag":"prose-paragraph","props":{},"children":[{"type":"text","value":"De uma idéia a uma obra-prima, guias levam você ao caminho para ser um Nuxter."}]}],"content":[{"type":"element","tag":"prose-paragraph","props":{},"children":[{"type":"text","value":"De uma idéia a uma obra-prima, guias levam você ao caminho para ser um Nuxter."}]}]}]},{"type":"text","value":"\n"},{"type":"element","tag":"home-explore","props":{"category":"Explore"},"children":[{"type":"element","tag":"section-content-item","props":{"description":"Amplie e automatize o seu fluxo de trabalho usando deploys para suas ferramentas favoritas.","image":"/img/home/explore/gem-explore-1.svg","title":"Deploy","hoverClass":"hover:bg-sky-surface","to":"/deployments"},"children":[]},{"type":"element","tag":"section-content-item","props":{"description":"Descubra nossa lista de módulos para dar super-poderes ao seu projeto Nuxt. Criado pelo time do Nuxt e pela comunidade.","image":"/img/home/explore/gem-explore-2.svg","title":"Módulos","hoverClass":"hover:bg-sky-surface","to":"https://modules.nuxtjs.org"},"children":[]},{"type":"element","tag":"section-content-item","props":{"description":"Veja como uma aplicação real é construída usando Nuxt com temas feitos pelos nossos parceiros.","image":"/img/home/explore/gem-explore-3.svg","title":"Temas","hoverClass":"hover:bg-sky-surface","to":"/themes"},"children":[]},{"type":"element","tag":"template","props":{"v-slot:title":""},"children":[{"type":"element","tag":"prose-paragraph","props":{},"children":[{"type":"text","value":"Seguindo em frente? Ainda têm muito pra "},{"type":"element","tag":"span","props":{"className":["text-primary"]},"children":[{"type":"element","tag":"prose-em","props":{},"children":[{"type":"text","value":"Explorar"}]}]}]}],"content":[{"type":"element","tag":"prose-paragraph","props":{},"children":[{"type":"text","value":"Seguindo em frente? Ainda têm muito pra "},{"type":"element","tag":"span","props":{"className":["text-primary"]},"children":[{"type":"element","tag":"prose-em","props":{},"children":[{"type":"text","value":"Explorar"}]}]}]}]},{"type":"element","tag":"template","props":{"v-slot:description":""},"children":[{"type":"element","tag":"prose-paragraph","props":{},"children":[{"type":"text","value":"Descubra módulos poderosos, integre-se com os seus provedores favoritos e comece rápido com os temas."}]}],"content":[{"type":"element","tag":"prose-paragraph","props":{},"children":[{"type":"text","value":"Descubra módulos poderosos, integre-se com os seus provedores favoritos e comece rápido com os temas."}]}]}]},{"type":"text","value":"\n"},{"type":"element","tag":"home-community","props":{"announcementsCategory":"Anúncios","articleLinkTitle":"Saiba mais","category":"Comunidade","eventsCategory":"Eventos"},"children":[{"type":"element","tag":"template","props":{"v-slot:title":""},"children":[{"type":"element","tag":"prose-paragraph","props":{},"children":[{"type":"text","value":"Compartilhar é "},{"type":"element","tag":"span","props":{"className":["text-sky-lighter"]},"children":[{"type":"text","value":"Cuidar"}]}]}],"content":[{"type":"element","tag":"prose-paragraph","props":{},"children":[{"type":"text","value":"Compartilhar é "},{"type":"element","tag":"span","props":{"className":["text-sky-lighter"]},"children":[{"type":"text","value":"Cuidar"}]}]}]},{"type":"element","tag":"template","props":{"v-slot:description":""},"children":[{"type":"element","tag":"prose-paragraph","props":{},"children":[{"type":"text","value":"Descubra artigos da equipe de estrutura e da comunidade sobre Nuxt. Dicas e truques incluídos!"}]}],"content":[{"type":"element","tag":"prose-paragraph","props":{},"children":[{"type":"text","value":"Descubra artigos da equipe de estrutura e da comunidade sobre Nuxt. Dicas e truques incluídos!"}]}]}]},{"type":"text","value":"\n"},{"type":"element","tag":"home-testimonials","props":{"category":"Comunidade"},"children":[{"type":"element","tag":"template","props":{"v-slot:title":""},"children":[{"type":"element","tag":"prose-paragraph","props":{},"children":[{"type":"text","value":"Depoimentos"}]}],"content":[{"type":"element","tag":"prose-paragraph","props":{},"children":[{"type":"text","value":"Depoimentos"}]}]},{"type":"element","tag":"template","props":{"v-slot:description":""},"children":[{"type":"element","tag":"prose-paragraph","props":{},"children":[{"type":"text","value":"Veja o que o especialistas adoram no Nuxt."}]}],"content":[{"type":"element","tag":"prose-paragraph","props":{},"children":[{"type":"text","value":"Veja o que o especialistas adoram no Nuxt."}]}]},{"type":"element","tag":"template","props":{"v-slot:testimonials":""},"children":[{"type":"element","tag":"testimonials","props":{":home":"true"},"children":[]}],"content":[{"type":"element","tag":"testimonials","props":{":home":"true"},"children":[]}]}]}]},"toc":{"title":"","searchDepth":2,"depth":2,"links":[]}}}