{"key":"content:ja:video-courses:index.md","generatedAt":"2022-03-15T12:42:48.571Z","mtime":"2022-03-15T12:42:48.560Z","slug":"","title":"Nuxt ビデオコース","position":"999999990000","to":"/video-courses","draft":false,"page":true,"language":"ja","template":"blog","description":"探索して無料およびプレミアムビデオコースで Nuxt フレームワークをより学びましょう。","empty":false,"body":{"raw":"---\ntemplate: blog\ntitle: Nuxt ビデオコース\ndescription: 探索して無料およびプレミアムビデオコースで Nuxt フレームワークをより学びましょう。\n---\n\n::video-courses-list\n---\nvideo-courses:\n  one:\n    title: 実世界で使えるアプリケーションを作って Nuxt を学習する\n    description: Nuxt を使って堅牢でモダンなウェブサイトをゼロから構築する方法を学びましょう。あるいは、フレームワークをより有効に活用しながら、ウェブサイトのパフォーマンスやコード品質を向上させましょう。\n    image: /img/video-courses/mastering_nuxt.png\n    link: 'https://masteringnuxt.com/?utm_source=nuxt&utm_medium=link&utm_campaign=navbar_link'\n    tier: プレミアム\n  two:\n    title: Nuxt で始める\n    description: 動的ルート、データ Fetch、SEO、遅延ローディング、グローバルスタイル、トランジションなど、Nuxt サイトを構築してデプロイするための必須事項を学び、Nuxt アプリを生成してデプロイする方法についてもご紹介します。\n    image: /img/video-courses/jamstack_explorer.png\n    link: 'https://explorers.netlify.com/learn/get-started-with-nuxt'\n    tier: 無料\n  three:\n    title: Debbie で Nuxt を学習する\n    description: ショートビデオやライブストリームなど、Nuxt のすべてを網羅した YouTube 動画のプレイリストです。\n    image: /img/video-courses/learn_nuxt_with_debbie.png\n    link: 'https://www.youtube.com/c/DebbieOBrien'\n    tier: 無料\n  four:\n    title: Vue と Nuxt でアプリケーションを作成する\n    description: Vue と Nuxt でダイナミックな Web アプリケーションを構築します! このコースでは、Vue CLI、Nuxt、Vuex Store などの Vue エコシステムのツールを活用して、さまざまなプロジェクトを構築します。\n    image: /img/video-courses/building_applications_fe_masters.png\n    link: 'https://frontendmasters.com/courses/vue-nuxt-apps/'\n    tier: プレミアム\n  five:\n    title: Laravel、GraphQL、Nuxt そして Appolo でジョブボードを作成する\n    description: Laravel Lighthouse で GraphQL API を構築し、Apollo で Nuxt のフロントエンドを構築して、それを消費しながら学習します。すべて Tailwind でスタイリングされています。\n    image: /img/video-courses/job_board.png\n    link: 'https://codecourse.com/courses/build-a-job-board-with-laravel-graphql-nuxt-and-apollo'\n    tier: プレミアム\n  six:\n    title: Nuxt - Vue.js on Steroids\n    description: Nuxt で魅力的な Vue JS アプリケーションを構築しましょう。Nuxt は、簡単なサーバーサイドレンダリングと、フォルダベースの設定方法を追加します。\n    image: /img/video-courses/vuejs_on_steroids.png\n    link: 'https://www.udemy.com/course/nuxtjs-vuejs-on-steroids/'\n    tier: プレミアム\n  seven:\n    title: Nuxt で Vue をスケーリングさせる\n    description: Vue に慣れてきたら、Nuxt のようなフレームワークを学ぶことで、ベストプラクティスに沿った制作可能な Web アプリを作ることができます。\n    image: /img/video-courses/scaling_vue_with_nuxt.png\n    link: 'https://www.vuemastery.com/courses/scaling-vue-with-nuxt-js/why-use-nuxt'\n    tier: プレミアム\n  eight:\n    title: Nuxt の基礎\n    description: このコースでは、Nuxt の基礎を Nuxt の創設者と一緒に作成しました。このコースでは、スキャフォールドから最初の Nuxt アプリケーションのデプロイまで、必要な知識をカバーしています。\n    image: /img/video-courses/nuxt_fundamentals.png\n    link: 'https://vueschool.io/courses/nuxtjs-fundamentals?friend=nuxt&utm_source=Nuxtjs.org&utm_medium=Link&utm_content=Courses&utm_campaign=nuxtjs-fundamentals'\n    tier: 無料\n  nine:\n    title: Vue.js と Nuxt でニュースアプリケーションを作成する\n    description: アプリケーションの各セクションにダイナミックページを作成し、データの読み込み、保存、表示、フィルタリング、スタイル設定を行う方法を学びます。最終的には、複数のカテゴリーページ、各セクションのコメント、ユーザーページを備えたニュースアプリケーションが完成します。\n    image: /img/video-courses/news_app.png\n    link: 'https://egghead.io/courses/create-a-news-app-with-vue-js-and-nuxt'\n    tier: 無料\n---\n::\n","ast":{"type":"root","children":[{"type":"element","tag":"video-courses-list","props":{":video-courses":"{\"one\":{\"title\":\"実世界で使えるアプリケーションを作って Nuxt を学習する\",\"description\":\"Nuxt を使って堅牢でモダンなウェブサイトをゼロから構築する方法を学びましょう。あるいは、フレームワークをより有効に活用しながら、ウェブサイトのパフォーマンスやコード品質を向上させましょう。\",\"image\":\"/img/video-courses/mastering_nuxt.png\",\"link\":\"https://masteringnuxt.com/?utm_source=nuxt&utm_medium=link&utm_campaign=navbar_link\",\"tier\":\"プレミアム\"},\"two\":{\"title\":\"Nuxt で始める\",\"description\":\"動的ルート、データ Fetch、SEO、遅延ローディング、グローバルスタイル、トランジションなど、Nuxt サイトを構築してデプロイするための必須事項を学び、Nuxt アプリを生成してデプロイする方法についてもご紹介します。\",\"image\":\"/img/video-courses/jamstack_explorer.png\",\"link\":\"https://explorers.netlify.com/learn/get-started-with-nuxt\",\"tier\":\"無料\"},\"three\":{\"title\":\"Debbie で Nuxt を学習する\",\"description\":\"ショートビデオやライブストリームなど、Nuxt のすべてを網羅した YouTube 動画のプレイリストです。\",\"image\":\"/img/video-courses/learn_nuxt_with_debbie.png\",\"link\":\"https://www.youtube.com/c/DebbieOBrien\",\"tier\":\"無料\"},\"four\":{\"title\":\"Vue と Nuxt でアプリケーションを作成する\",\"description\":\"Vue と Nuxt でダイナミックな Web アプリケーションを構築します! このコースでは、Vue CLI、Nuxt、Vuex Store などの Vue エコシステムのツールを活用して、さまざまなプロジェクトを構築します。\",\"image\":\"/img/video-courses/building_applications_fe_masters.png\",\"link\":\"https://frontendmasters.com/courses/vue-nuxt-apps/\",\"tier\":\"プレミアム\"},\"five\":{\"title\":\"Laravel、GraphQL、Nuxt そして Appolo でジョブボードを作成する\",\"description\":\"Laravel Lighthouse で GraphQL API を構築し、Apollo で Nuxt のフロントエンドを構築して、それを消費しながら学習します。すべて Tailwind でスタイリングされています。\",\"image\":\"/img/video-courses/job_board.png\",\"link\":\"https://codecourse.com/courses/build-a-job-board-with-laravel-graphql-nuxt-and-apollo\",\"tier\":\"プレミアム\"},\"six\":{\"title\":\"Nuxt - Vue.js on Steroids\",\"description\":\"Nuxt で魅力的な Vue JS アプリケーションを構築しましょう。Nuxt は、簡単なサーバーサイドレンダリングと、フォルダベースの設定方法を追加します。\",\"image\":\"/img/video-courses/vuejs_on_steroids.png\",\"link\":\"https://www.udemy.com/course/nuxtjs-vuejs-on-steroids/\",\"tier\":\"プレミアム\"},\"seven\":{\"title\":\"Nuxt で Vue をスケーリングさせる\",\"description\":\"Vue に慣れてきたら、Nuxt のようなフレームワークを学ぶことで、ベストプラクティスに沿った制作可能な Web アプリを作ることができます。\",\"image\":\"/img/video-courses/scaling_vue_with_nuxt.png\",\"link\":\"https://www.vuemastery.com/courses/scaling-vue-with-nuxt-js/why-use-nuxt\",\"tier\":\"プレミアム\"},\"eight\":{\"title\":\"Nuxt の基礎\",\"description\":\"このコースでは、Nuxt の基礎を Nuxt の創設者と一緒に作成しました。このコースでは、スキャフォールドから最初の Nuxt アプリケーションのデプロイまで、必要な知識をカバーしています。\",\"image\":\"/img/video-courses/nuxt_fundamentals.png\",\"link\":\"https://vueschool.io/courses/nuxtjs-fundamentals?friend=nuxt&utm_source=Nuxtjs.org&utm_medium=Link&utm_content=Courses&utm_campaign=nuxtjs-fundamentals\",\"tier\":\"無料\"},\"nine\":{\"title\":\"Vue.js と Nuxt でニュースアプリケーションを作成する\",\"description\":\"アプリケーションの各セクションにダイナミックページを作成し、データの読み込み、保存、表示、フィルタリング、スタイル設定を行う方法を学びます。最終的には、複数のカテゴリーページ、各セクションのコメント、ユーザーページを備えたニュースアプリケーションが完成します。\",\"image\":\"/img/video-courses/news_app.png\",\"link\":\"https://egghead.io/courses/create-a-news-app-with-vue-js-and-nuxt\",\"tier\":\"無料\"}}"},"children":[]}]},"toc":{"title":"","searchDepth":2,"depth":2,"links":[]}}}